{"regions": [{"name": "Arecibo", "totalClients": 177369, "totalClientsWithoutService": 747, "totalClientsWithService": 176622, "totalClientsAffectedByPlannedOutage": 0, "percentageClientsWithoutService": 0.42, "percentageClientsWithService": 99.58}, {"name": "Bayamon", "totalClients": 216496, "totalClientsWithoutService": 2703, "totalClientsWithService": 213793, "totalClientsAffectedByPlannedOutage": 0, "percentageClientsWithoutService": 1.25, "percentageClientsWithService": 98.75}, {"name": "Mayaguez", "totalClients": 216605, "totalClientsWithoutService": 503, "totalClientsWithService": 216102, "totalClientsAffectedByPlannedOutage": 0, "percentageClientsWithoutService": 0.23, "percentageClientsWithService": 99.77}, {"name": "San Juan", "totalClients": 253068, "totalClientsWithoutService": 4063, "totalClientsWithService": 249005, "totalClientsAffectedByPlannedOutage": 344, "percentageClientsWithoutService": 1.61, "percentageClientsWithService": 98.39}, {"name": "Carolina", "totalClients": 141663, "totalClientsWithoutService": 93, "totalClientsWithService": 141570, "totalClientsAffectedByPlannedOutage": 0, "percentageClientsWithoutService": 0.07, "percentageClientsWithService": 99.93}, {"name": "Caguas", "totalClients": 250514, "totalClientsWithoutService": 939, "totalClientsWithService": 249575, "totalClientsAffectedByPlannedOutage": 14, "percentageClientsWithoutService": 0.37, "percentageClientsWithService": 99.63}, {"name": "Ponce", "totalClients": 212508, "totalClientsWithoutService": 18, "totalClientsWithService": 212490, "totalClientsAffectedByPlannedOutage": 0, "percentageClientsWithoutService": 0.01, "percentageClientsWithService": 99.99}], "totals": {"totalClientsWithoutService": 9066, "totalClients": 1468223, "totalClientsWithService": 1459157, "totalPercentageWithoutService": 0.62, "totalClientsAffectedByPlannedOutage": 358, "totalPercentageWithService": 99.38}, "timestamp": "07/22/2024 01:00 PM"}