{"regions": [{"name": "Arecibo", "totalClients": 177369, "totalClientsWithoutService": 106, "totalClientsWithService": 177263, "totalClientsAffectedByPlannedOutage": 0, "percentageClientsWithoutService": 0.06, "percentageClientsWithService": 99.94}, {"name": "Mayaguez", "totalClients": 216605, "totalClientsWithoutService": 1359, "totalClientsWithService": 215246, "totalClientsAffectedByPlannedOutage": 9, "percentageClientsWithoutService": 0.63, "percentageClientsWithService": 99.37}, {"name": "Bayamon", "totalClients": 216496, "totalClientsWithoutService": 2320, "totalClientsWithService": 214176, "totalClientsAffectedByPlannedOutage": 1566, "percentageClientsWithoutService": 1.07, "percentageClientsWithService": 98.93}, {"name": "San Juan", "totalClients": 253068, "totalClientsWithoutService": 827, "totalClientsWithService": 252241, "totalClientsAffectedByPlannedOutage": 176, "percentageClientsWithoutService": 0.33, "percentageClientsWithService": 99.67}, {"name": "Carolina", "totalClients": 141663, "totalClientsWithoutService": 118, "totalClientsWithService": 141545, "totalClientsAffectedByPlannedOutage": 100, "percentageClientsWithoutService": 0.08, "percentageClientsWithService": 99.92}, {"name": "Caguas", "totalClients": 250514, "totalClientsWithoutService": 671, "totalClientsWithService": 249843, "totalClientsAffectedByPlannedOutage": 83, "percentageClientsWithoutService": 0.27, "percentageClientsWithService": 99.73}, {"name": "Ponce", "totalClients": 212508, "totalClientsWithoutService": 4264, "totalClientsWithService": 208244, "totalClientsAffectedByPlannedOutage": 4135, "percentageClientsWithoutService": 2.01, "percentageClientsWithService": 97.99}], "totals": {"totalClientsWithoutService": 9665, "totalClients": 1468223, "totalClientsWithService": 1458558, "totalPercentageWithoutService": 0.66, "totalClientsAffectedByPlannedOutage": 6069, "totalPercentageWithService": 99.34}, "timestamp": "01/21/2025 12:00 PM"}