{"regions": [{"name": "Arecibo", "totalClients": 177369, "totalClientsWithoutService": 188, "totalClientsWithService": 177181, "percentageClientsWithoutService": 0.11, "percentageClientsWithService": 99.89}, {"name": "Bayamon", "totalClients": 216496, "totalClientsWithoutService": 2052, "totalClientsWithService": 214444, "percentageClientsWithoutService": 0.95, "percentageClientsWithService": 99.05}, {"name": "Carolina", "totalClients": 141663, "totalClientsWithoutService": 18, "totalClientsWithService": 141645, "percentageClientsWithoutService": 0.01, "percentageClientsWithService": 99.99}, {"name": "Caguas", "totalClients": 250514, "totalClientsWithoutService": 1998, "totalClientsWithService": 248516, "percentageClientsWithoutService": 0.8, "percentageClientsWithService": 99.2}, {"name": "Mayaguez", "totalClients": 216605, "totalClientsWithoutService": 1266, "totalClientsWithService": 215339, "percentageClientsWithoutService": 0.58, "percentageClientsWithService": 99.42}, {"name": "Ponce", "totalClients": 212508, "totalClientsWithoutService": 605, "totalClientsWithService": 211903, "percentageClientsWithoutService": 0.28, "percentageClientsWithService": 99.72}, {"name": "San Juan", "totalClients": 253068, "totalClientsWithoutService": 107, "totalClientsWithService": 252961, "percentageClientsWithoutService": 0.04, "percentageClientsWithService": 99.96}], "totals": {"totalClientsWithoutService": 6234, "totalClients": 1468223, "totalClientsWithService": 1461989, "totalPercentageWithoutService": 0.42, "totalPercentageWithService": 99.58}, "timestamp": "06/05/2023 04:00 PM"}