{"regions": [{"name": "Arecibo", "totalClients": 177369, "totalClientsWithoutService": 134, "totalClientsWithService": 177235, "percentageClientsWithoutService": 0.08, "percentageClientsWithService": 99.92}, {"name": "Bayamon", "totalClients": 216496, "totalClientsWithoutService": 471, "totalClientsWithService": 216025, "percentageClientsWithoutService": 0.22, "percentageClientsWithService": 99.78}, {"name": "Carolina", "totalClients": 141663, "totalClientsWithoutService": 425, "totalClientsWithService": 141238, "percentageClientsWithoutService": 0.3, "percentageClientsWithService": 99.7}, {"name": "Caguas", "totalClients": 250514, "totalClientsWithoutService": 28, "totalClientsWithService": 250486, "percentageClientsWithoutService": 0.01, "percentageClientsWithService": 99.99}, {"name": "Mayaguez", "totalClients": 216605, "totalClientsWithoutService": 1021, "totalClientsWithService": 215584, "percentageClientsWithoutService": 0.47, "percentageClientsWithService": 99.53}, {"name": "Ponce", "totalClients": 212508, "totalClientsWithoutService": 266, "totalClientsWithService": 212242, "percentageClientsWithoutService": 0.13, "percentageClientsWithService": 99.87}, {"name": "San Juan", "totalClients": 253068, "totalClientsWithoutService": 61, "totalClientsWithService": 253007, "percentageClientsWithoutService": 0.02, "percentageClientsWithService": 99.98}], "totals": {"totalClientsWithoutService": 2406, "totalClients": 1468223, "totalClientsWithService": 1465817, "totalPercentageWithoutService": 0.16, "totalPercentageWithService": 99.84}, "timestamp": "05/28/2023 01:00 AM"}