{"regions": [{"name": "Arecibo", "totalClients": 177369, "totalClientsWithoutService": 514, "totalClientsWithService": 176855, "totalClientsAffectedByPlannedOutage": 0, "totalClientsAffectedByLoadShed": 0, "percentageClientsWithoutService": 0.29, "percentageClientsWithService": 99.71}, {"name": "Bayamon", "totalClients": 216496, "totalClientsWithoutService": 297, "totalClientsWithService": 216199, "totalClientsAffectedByPlannedOutage": 0, "totalClientsAffectedByLoadShed": 0, "percentageClientsWithoutService": 0.14, "percentageClientsWithService": 99.86}, {"name": "Carolina", "totalClients": 141663, "totalClientsWithoutService": 2, "totalClientsWithService": 141661, "totalClientsAffectedByPlannedOutage": 0, "totalClientsAffectedByLoadShed": 0, "percentageClientsWithoutService": 0.0, "percentageClientsWithService": 100.0}, {"name": "Caguas", "totalClients": 250514, "totalClientsWithoutService": 1106, "totalClientsWithService": 249408, "totalClientsAffectedByPlannedOutage": 79, "totalClientsAffectedByLoadShed": 0, "percentageClientsWithoutService": 0.44, "percentageClientsWithService": 99.56}, {"name": "Mayaguez", "totalClients": 216605, "totalClientsWithoutService": 4836, "totalClientsWithService": 211769, "totalClientsAffectedByPlannedOutage": 0, "totalClientsAffectedByLoadShed": 0, "percentageClientsWithoutService": 2.23, "percentageClientsWithService": 97.77}, {"name": "Ponce", "totalClients": 212508, "totalClientsWithoutService": 946, "totalClientsWithService": 211562, "totalClientsAffectedByPlannedOutage": 0, "totalClientsAffectedByLoadShed": 0, "percentageClientsWithoutService": 0.45, "percentageClientsWithService": 99.55}, {"name": "San Juan", "totalClients": 253068, "totalClientsWithoutService": 163, "totalClientsWithService": 252905, "totalClientsAffectedByPlannedOutage": 0, "totalClientsAffectedByLoadShed": 0, "percentageClientsWithoutService": 0.06, "percentageClientsWithService": 99.94}], "totals": {"totalClientsWithoutService": 7864, "totalClientsAffectedByLoadShed": 0, "totalClients": 1468223, "totalClientsWithService": 1460359, "totalPercentageWithoutService": 0.54, "totalClientsAffectedByPlannedOutage": 79, "totalPercentageWithService": 99.46}, "timestamp": "11/09/2025 03:00 PM"}