{"regions": [{"name": "Arecibo", "totalClients": 177369, "totalClientsWithoutService": 767, "totalClientsWithService": 176602, "totalClientsAffectedByPlannedOutage": 0, "percentageClientsWithoutService": 0.43, "percentageClientsWithService": 99.57}, {"name": "Mayaguez", "totalClients": 216605, "totalClientsWithoutService": 73, "totalClientsWithService": 216532, "totalClientsAffectedByPlannedOutage": 0, "percentageClientsWithoutService": 0.03, "percentageClientsWithService": 99.97}, {"name": "Bayamon", "totalClients": 216496, "totalClientsWithoutService": 523, "totalClientsWithService": 215973, "totalClientsAffectedByPlannedOutage": 0, "percentageClientsWithoutService": 0.24, "percentageClientsWithService": 99.76}, {"name": "San Juan", "totalClients": 253068, "totalClientsWithoutService": 383, "totalClientsWithService": 252685, "totalClientsAffectedByPlannedOutage": 0, "percentageClientsWithoutService": 0.15, "percentageClientsWithService": 99.85}, {"name": "Carolina", "totalClients": 141663, "totalClientsWithoutService": 1245, "totalClientsWithService": 140418, "totalClientsAffectedByPlannedOutage": 0, "percentageClientsWithoutService": 0.88, "percentageClientsWithService": 99.12}, {"name": "Ponce", "totalClients": 212508, "totalClientsWithoutService": 142, "totalClientsWithService": 212366, "totalClientsAffectedByPlannedOutage": 0, "percentageClientsWithoutService": 0.07, "percentageClientsWithService": 99.93}, {"name": "Caguas", "totalClients": 250514, "totalClientsWithoutService": 589, "totalClientsWithService": 249925, "totalClientsAffectedByPlannedOutage": 0, "percentageClientsWithoutService": 0.24, "percentageClientsWithService": 99.76}], "totals": {"totalClientsWithoutService": 3722, "totalClients": 1468223, "totalClientsWithService": 1464501, "totalPercentageWithoutService": 0.25, "totalClientsAffectedByPlannedOutage": 0, "totalPercentageWithService": 99.75}, "timestamp": "08/26/2024 09:00 AM"}