{"regions": [{"name": "Arecibo", "totalClients": 177369, "totalClientsWithoutService": 1, "percentageClientsWithoutService": 0.0}, {"name": "Bayamon", "totalClients": 216496, "totalClientsWithoutService": 863, "percentageClientsWithoutService": 0.4}, {"name": "Carolina", "totalClients": 141663, "totalClientsWithoutService": 3, "percentageClientsWithoutService": 0.0}, {"name": "Caguas", "totalClients": 250514, "totalClientsWithoutService": 122, "percentageClientsWithoutService": 0.05}, {"name": "Mayaguez", "totalClients": 216605, "totalClientsWithoutService": 189, "percentageClientsWithoutService": 0.09}, {"name": "Ponce", "totalClients": 212508, "totalClientsWithoutService": 40, "percentageClientsWithoutService": 0.02}, {"name": "San Juan", "totalClients": 253068, "totalClientsWithoutService": 187, "percentageClientsWithoutService": 0.07}], "totals": {"totalClientsWithoutService": 1405, "totalClients": 1468223, "totalPercentage": 0.1}}