{"regions": [{"name": "Arecibo", "totalClients": 177369, "totalClientsWithoutService": 6054, "totalClientsWithService": 171315, "totalClientsAffectedByPlannedOutage": 0, "percentageClientsWithoutService": 3.41, "percentageClientsWithService": 96.59}, {"name": "Bayamon", "totalClients": 216496, "totalClientsWithoutService": 3619, "totalClientsWithService": 212877, "totalClientsAffectedByPlannedOutage": 340, "percentageClientsWithoutService": 1.67, "percentageClientsWithService": 98.33}, {"name": "Mayaguez", "totalClients": 216605, "totalClientsWithoutService": 151, "totalClientsWithService": 216454, "totalClientsAffectedByPlannedOutage": 0, "percentageClientsWithoutService": 0.07, "percentageClientsWithService": 99.93}, {"name": "San Juan", "totalClients": 253068, "totalClientsWithoutService": 1102, "totalClientsWithService": 251966, "totalClientsAffectedByPlannedOutage": 455, "percentageClientsWithoutService": 0.44, "percentageClientsWithService": 99.56}, {"name": "Carolina", "totalClients": 141663, "totalClientsWithoutService": 58, "totalClientsWithService": 141605, "totalClientsAffectedByPlannedOutage": 0, "percentageClientsWithoutService": 0.04, "percentageClientsWithService": 99.96}, {"name": "Ponce", "totalClients": 212508, "totalClientsWithoutService": 919, "totalClientsWithService": 211589, "totalClientsAffectedByPlannedOutage": 866, "percentageClientsWithoutService": 0.43, "percentageClientsWithService": 99.57}, {"name": "Caguas", "totalClients": 250514, "totalClientsWithoutService": 1751, "totalClientsWithService": 248763, "totalClientsAffectedByPlannedOutage": 1271, "percentageClientsWithoutService": 0.7, "percentageClientsWithService": 99.3}], "totals": {"totalClientsWithoutService": 13654, "totalClients": 1468223, "totalClientsWithService": 1454569, "totalPercentageWithoutService": 0.93, "totalClientsAffectedByPlannedOutage": 2932, "totalPercentageWithService": 99.07}, "timestamp": "07/23/2024 02:00 PM"}