{"regions": [{"name": "Arecibo", "totalClients": 177369, "totalClientsWithoutService": 152, "totalClientsWithService": 177217, "percentageClientsWithoutService": 0.09, "percentageClientsWithService": 99.91}, {"name": "Bayamon", "totalClients": 216496, "totalClientsWithoutService": 8780, "totalClientsWithService": 207716, "percentageClientsWithoutService": 4.06, "percentageClientsWithService": 95.94}, {"name": "Carolina", "totalClients": 141663, "totalClientsWithoutService": 262, "totalClientsWithService": 141401, "percentageClientsWithoutService": 0.18, "percentageClientsWithService": 99.82}, {"name": "Caguas", "totalClients": 250514, "totalClientsWithoutService": 1463, "totalClientsWithService": 249051, "percentageClientsWithoutService": 0.58, "percentageClientsWithService": 99.42}, {"name": "Mayaguez", "totalClients": 216605, "totalClientsWithoutService": 70, "totalClientsWithService": 216535, "percentageClientsWithoutService": 0.03, "percentageClientsWithService": 99.97}, {"name": "Ponce", "totalClients": 212508, "totalClientsWithoutService": 649, "totalClientsWithService": 211859, "percentageClientsWithoutService": 0.31, "percentageClientsWithService": 99.69}, {"name": "San Juan", "totalClients": 253068, "totalClientsWithoutService": 2016, "totalClientsWithService": 251052, "percentageClientsWithoutService": 0.8, "percentageClientsWithService": 99.2}], "totals": {"totalClientsWithoutService": 13392, "totalClients": 1468223, "totalClientsWithService": 1454831, "totalPercentageWithoutService": 0.91, "totalPercentageWithService": 99.09}, "timestamp": "05/26/2023 05:00 PM"}