{"regions": [{"name": "Arecibo", "totalClients": 177369, "totalClientsWithoutService": 608, "totalClientsWithService": 176761, "totalClientsAffectedByPlannedOutage": 11, "percentageClientsWithoutService": 0.34, "percentageClientsWithService": 99.66}, {"name": "Bayamon", "totalClients": 216496, "totalClientsWithoutService": 875, "totalClientsWithService": 215621, "totalClientsAffectedByPlannedOutage": 418, "percentageClientsWithoutService": 0.4, "percentageClientsWithService": 99.6}, {"name": "Mayaguez", "totalClients": 216605, "totalClientsWithoutService": 845, "totalClientsWithService": 215760, "totalClientsAffectedByPlannedOutage": 823, "percentageClientsWithoutService": 0.39, "percentageClientsWithService": 99.61}, {"name": "San Juan", "totalClients": 253068, "totalClientsWithoutService": 251, "totalClientsWithService": 252817, "totalClientsAffectedByPlannedOutage": 0, "percentageClientsWithoutService": 0.1, "percentageClientsWithService": 99.9}, {"name": "Carolina", "totalClients": 141663, "totalClientsWithoutService": 65, "totalClientsWithService": 141598, "totalClientsAffectedByPlannedOutage": 0, "percentageClientsWithoutService": 0.05, "percentageClientsWithService": 99.95}, {"name": "Caguas", "totalClients": 250514, "totalClientsWithoutService": 4271, "totalClientsWithService": 246243, "totalClientsAffectedByPlannedOutage": 0, "percentageClientsWithoutService": 1.7, "percentageClientsWithService": 98.3}, {"name": "Ponce", "totalClients": 212508, "totalClientsWithoutService": 503, "totalClientsWithService": 212005, "totalClientsAffectedByPlannedOutage": 445, "percentageClientsWithoutService": 0.24, "percentageClientsWithService": 99.76}], "totals": {"totalClientsWithoutService": 7418, "totalClients": 1468223, "totalClientsWithService": 1460805, "totalPercentageWithoutService": 0.51, "totalClientsAffectedByPlannedOutage": 1697, "totalPercentageWithService": 99.49}, "timestamp": "11/25/2024 11:00 AM"}