{"LUQUILLO": [{"zone": "Bo. Pitahaya", "area": "LUQUILLO"}], "COROZAL": [], "CIALES": [{"zone": "BO CORDILLERA", "area": "CIALES"}], "LAS MARIAS": [], "PATILLAS": [{"zone": "BO LOS RIOS SECTOR LOS MORALES", "area": "PATILLAS"}], "DORADO": [], "GUAYAMA": [], "HATILLO": [], "GUAYANILLA": [], "BARCELONETA": [], "AGUAS BUENAS": [], "HUMACAO": [], "VIEQUES": [], "FLORIDA": [], "LOIZA": [{"zone": "CANOVANAS", "area": "LOIZA"}], "RIO GRANDE": [], "COMERIO": [], "VEGA ALTA": [], "AIBONITO": [], "RINCON": [], "ANASCO": [], "CIDRA": [], "MOCA": [], "YABUCOA": [], "JUANA DIAZ": [], "LARES": [], "OROCOVIS": [], "ARECIBO": [], "TOA ALTA": [], "LAJAS": [{"zone": "PALMAREJO", "area": "LAJAS"}], "PE\u00d1UELAS": [], "ISABELLA": [], "SABANA GRANDE": [], "SANTA ISABEL": [], "SALINAS": [], "SAN SEBASTIAN": [], "HORMIGUEROS": [], "AGUADILLA": [], "CULEBRA": [], "QUEBRADILLAS": [], "GUAYNABO": [{"zone": "URB. GARDEN HILLS SUR", "area": "GUAYNABO"}], "JUNCOS": [], "CABO ROJO": [{"zone": "BO. BAJURAS", "area": "CABO ROJO"}], "CATANO": [], "CAROLINA": [], "BARRANQUITAS": [{"zone": "URB JARD BQTAS CALLE C BL C-32", "area": "BARRANQUITAS"}], "ADJUNTAS": [{"zone": "PELLEJAS", "area": "ADJUNTAS"}], "SAN GERMAN": [{"zone": "CAIN ALTO", "area": "SAN GERMAN"}, {"zone": "SEC CAMINO POMPEYO DUEY ALTO", "area": "SAN GERMAN"}], "TOA BAJA": [{"zone": "Bo. Candelaria Arenas", "area": "TOA BAJA"}], "BAYAMON": [], "ARROYO": [], "CANOVANAS": [], "AGUADA": [], "VILLALBA": [], "GURABO": [{"zone": "GURABO", "area": "GURABO"}], "MARICAO": [], "LAS PIEDRAS": [], "TRUJILLO ALTO": [{"zone": "QUEBRADA GRANDE", "area": "TRUJILLO ALTO"}], "CAMUY": [], "PONCE": [], "JAYUYA": [], "CAYEY": [], "MANATI": [{"zone": "RIO ARRIBA SALIENTE", "area": "MANATI"}], "COAMO": [], "UTUADO": [], "NAGUABO": [], "SAN JUAN": [{"zone": "URB LAGO ALTO", "area": "SAN JUAN"}, {"zone": "Urb. Caldas", "area": "SAN JUAN"}], "GUANICA": [], "CAGUAS": [], "CEIBA": [], "MOROVIS": [], "NARANJITO": [], "VEGA BAJA": [], "SAN LORENZO": [{"zone": "QUEBRADA HONDA", "area": "SAN LORENZO"}], "FAJARDO": [], "MAYAGUEZ": [{"zone": "CLINICA DE VETERANOS", "area": "MAYAGUEZ"}, {"zone": "MONTOSO", "area": "MAYAGUEZ"}], "MAUNABO": [], "YAUCO": []}