{"regions": [{"name": "Arecibo", "totalClients": 177369, "totalClientsWithoutService": 1800, "totalClientsWithService": 175569, "totalClientsAffectedByPlannedOutage": 0, "totalClientsAffectedByLoadShed": 0, "percentageClientsWithoutService": 1.01, "percentageClientsWithService": 98.99}, {"name": "Bayamon", "totalClients": 216496, "totalClientsWithoutService": 5671, "totalClientsWithService": 210825, "totalClientsAffectedByPlannedOutage": 0, "totalClientsAffectedByLoadShed": 0, "percentageClientsWithoutService": 2.62, "percentageClientsWithService": 97.38}, {"name": "Carolina", "totalClients": 141663, "totalClientsWithoutService": 3, "totalClientsWithService": 141660, "totalClientsAffectedByPlannedOutage": 0, "totalClientsAffectedByLoadShed": 0, "percentageClientsWithoutService": 0.0, "percentageClientsWithService": 100.0}, {"name": "Caguas", "totalClients": 250514, "totalClientsWithoutService": 91, "totalClientsWithService": 250423, "totalClientsAffectedByPlannedOutage": 0, "totalClientsAffectedByLoadShed": 0, "percentageClientsWithoutService": 0.04, "percentageClientsWithService": 99.96}, {"name": "Mayaguez", "totalClients": 216605, "totalClientsWithoutService": 296, "totalClientsWithService": 216309, "totalClientsAffectedByPlannedOutage": 0, "totalClientsAffectedByLoadShed": 0, "percentageClientsWithoutService": 0.14, "percentageClientsWithService": 99.86}, {"name": "Ponce", "totalClients": 212508, "totalClientsWithoutService": 9, "totalClientsWithService": 212499, "totalClientsAffectedByPlannedOutage": 0, "totalClientsAffectedByLoadShed": 0, "percentageClientsWithoutService": 0.0, "percentageClientsWithService": 100.0}, {"name": "San Juan", "totalClients": 253068, "totalClientsWithoutService": 408, "totalClientsWithService": 252660, "totalClientsAffectedByPlannedOutage": 0, "totalClientsAffectedByLoadShed": 0, "percentageClientsWithoutService": 0.16, "percentageClientsWithService": 99.84}], "totals": {"totalClientsWithoutService": 8278, "totalClientsAffectedByLoadShed": 0, "totalClients": 1468223, "totalClientsWithService": 1459945, "totalPercentageWithoutService": 0.56, "totalClientsAffectedByPlannedOutage": 0, "totalPercentageWithService": 99.44}, "timestamp": "10/13/2025 10:00 AM"}