{"regions": [{"name": "Arecibo", "totalClients": 177369, "totalClientsWithoutService": 3850, "totalClientsWithService": 173519, "percentageClientsWithoutService": 2.17, "percentageClientsWithService": 97.83}, {"name": "Bayamon", "totalClients": 216496, "totalClientsWithoutService": 1249, "totalClientsWithService": 215247, "percentageClientsWithoutService": 0.58, "percentageClientsWithService": 99.42}, {"name": "Carolina", "totalClients": 141663, "totalClientsWithoutService": 4, "totalClientsWithService": 141659, "percentageClientsWithoutService": 0.0, "percentageClientsWithService": 100.0}, {"name": "Caguas", "totalClients": 250514, "totalClientsWithoutService": 974, "totalClientsWithService": 249540, "percentageClientsWithoutService": 0.39, "percentageClientsWithService": 99.61}, {"name": "Mayaguez", "totalClients": 216605, "totalClientsWithoutService": 4086, "totalClientsWithService": 212519, "percentageClientsWithoutService": 1.89, "percentageClientsWithService": 98.11}, {"name": "Ponce", "totalClients": 212508, "totalClientsWithoutService": 1966, "totalClientsWithService": 210542, "percentageClientsWithoutService": 0.93, "percentageClientsWithService": 99.07}, {"name": "San Juan", "totalClients": 253068, "totalClientsWithoutService": 7400, "totalClientsWithService": 245668, "percentageClientsWithoutService": 2.92, "percentageClientsWithService": 97.08}], "totals": {"totalClientsWithoutService": 19529, "totalClients": 1468223, "totalClientsWithService": 1448694, "totalPercentageWithoutService": 1.33, "totalPercentageWithService": 98.67}, "timestamp": "10/26/2023 02:00 PM"}