{"LUQUILLO": [{"zone": "BO RIO CHIQUITO", "area": "LUQUILLO"}, {"zone": "Bo. Mata De Platano", "area": "LUQUILLO"}, {"zone": "Bo. Pitahaya", "area": "LUQUILLO"}, {"zone": "Urb. Vistas De Luquill", "area": "LUQUILLO"}], "COROZAL": [{"zone": "BO CIBUCO SECTOR JULIO ORTEGA", "area": "COROZAL"}, {"zone": "BO MANA ESCUELAS", "area": "COROZAL"}, {"zone": "BO PADILLA SECTOR IGLESIA", "area": "COROZAL"}, {"zone": "Bo. Abras", "area": "COROZAL"}, {"zone": "PALMAREJO", "area": "COROZAL"}], "CIALES": [{"zone": "  -  ", "area": "CIALES"}, {"zone": "BO FRONTON YUNES", "area": "CIALES"}], "LAS MARIAS": [{"zone": "BO ESPINO", "area": "LAS MARIAS"}, {"zone": "BO. MARAVILLA SUR", "area": "LAS MARIAS"}, {"zone": "Bo. Cerrote", "area": "LAS MARIAS"}, {"zone": "Bo. Maravilla Norte", "area": "LAS MARIAS"}, {"zone": "Bo. Maravilla Sur", "area": "LAS MARIAS"}], "PATILLAS": [{"zone": "  -  ", "area": "PATILLAS"}], "DORADO": [{"zone": "BO SANTA ROSA", "area": "DORADO"}, {"zone": "HIGUILLAR", "area": "DORADO"}, {"zone": "MAMEYAL  LA PLAYA DE KIKITA", "area": "DORADO"}, {"zone": "PAR 234 BO RIO LAJAS", "area": "DORADO"}, {"zone": "URB PAISAJES DE DORADO", "area": "DORADO"}, {"zone": "Urb. Dorado Beach East", "area": "DORADO"}], "GUAYAMA": [{"zone": "ALGARROBO", "area": "GUAYAMA"}, {"zone": "BO PUEBLITO DEL CARMEN", "area": "GUAYAMA"}, {"zone": "Bo. Puente De Jobos", "area": "GUAYAMA"}, {"zone": "EL LEGADO GOLF RESORT", "area": "GUAYAMA"}, {"zone": "JOBOS", "area": "GUAYAMA"}, {"zone": "MACHETE", "area": "GUAYAMA"}, {"zone": "URB COSTA AZUL", "area": "GUAYAMA"}, {"zone": "URB SAN MARTIN", "area": "GUAYAMA"}, {"zone": "Urb. Caribe Mar", "area": "GUAYAMA"}], "HATILLO": [{"zone": "AIBONITO", "area": "HATILLO"}, {"zone": "BO CAPAEZ/", "area": "HATILLO"}, {"zone": "BO PAJUIL", "area": "HATILLO"}, {"zone": "BO PUEBLO CALLE GUAMA 181", "area": "HATILLO"}, {"zone": "BO.CARRIZALEZ/ORATORIO", "area": "HATILLO"}, {"zone": "Bo. Campo Alegre", "area": "HATILLO"}, {"zone": "CARRIZALES-SEC QUINTO SOTO", "area": "HATILLO"}], "GUAYANILLA": [{"zone": "BO INDIOS SECTOR LOS TORRES", "area": "GUAYANILLA"}, {"zone": "BO MAGAS", "area": "GUAYANILLA"}], "BARCELONETA": [{"zone": "BO LLANADAS", "area": "BARCELONETA"}, {"zone": "Bo. Magueyes", "area": "BARCELONETA"}, {"zone": "FLORIDA AFUERA", "area": "BARCELONETA"}, {"zone": "PARC BUFALO", "area": "BARCELONETA"}, {"zone": "URB. ESTANCIAS BARCELO", "area": "BARCELONETA"}], "AGUAS BUENAS": [{"zone": "BO BAIROA/SECT EL PERICO", "area": "AGUAS BUENAS"}, {"zone": "BO SUMIDERO/SECT JACANA", "area": "AGUAS BUENAS"}, {"zone": "Bo. Jagueyes", "area": "AGUAS BUENAS"}, {"zone": "Casco Urbano Aguas Buenas", "area": "AGUAS BUENAS"}, {"zone": "SECT MINILLASBO. MULAS", "area": "AGUAS BUENAS"}], "HUMACAO": [{"zone": "BO TEJAS RL 018", "area": "HUMACAO"}, {"zone": "Bo. Candelero Arriba", "area": "HUMACAO"}, {"zone": "MARIANA 26049", "area": "HUMACAO"}, {"zone": "PALMAS DEL MAR      RUTA 26066", "area": "HUMACAO"}, {"zone": "PLAYA", "area": "HUMACAO"}, {"zone": "URB LOS ROSALES", "area": "HUMACAO"}, {"zone": "URB VERDE MAR", "area": "HUMACAO"}, {"zone": "URB VILLAS DEL RIO 26005", "area": "HUMACAO"}], "VIEQUES": [], "FLORIDA": [{"zone": "BO PAJONAL SECT DORTA", "area": "FLORIDA"}, {"zone": "URB. ALTURAS DE FLORID", "area": "FLORIDA"}, {"zone": "Urb. Altos De Florida", "area": "FLORIDA"}], "LOIZA": [{"zone": "Bo. Las Carreras", "area": "LOIZA"}, {"zone": "Bo. Mediania Alta", "area": "LOIZA"}, {"zone": "LOIZA", "area": "LOIZA"}, {"zone": "MEDIANIA BAJA", "area": "LOIZA"}], "RIO GRANDE": [{"zone": "  -  ", "area": "RIO GRANDE"}, {"zone": "BO MALPICA", "area": "RIO GRANDE"}, {"zone": "BO. JIMENEZ", "area": "RIO GRANDE"}, {"zone": "Bo. Carola", "area": "RIO GRANDE"}, {"zone": "Bo. Guzman Arriba", "area": "RIO GRANDE"}, {"zone": "CIENAGA ALTA", "area": "RIO GRANDE"}, {"zone": "CIENAGA BAJA", "area": "RIO GRANDE"}, {"zone": "Cond. Casa Del Mar", "area": "RIO GRANDE"}, {"zone": "GUZMAN ABAJO", "area": "RIO GRANDE"}, {"zone": "GUZMAN ARRIBA", "area": "RIO GRANDE"}, {"zone": "MALPICA", "area": "RIO GRANDE"}, {"zone": "Urb. Alturas Rio Grande", "area": "RIO GRANDE"}, {"zone": "ZARZAL", "area": "RIO GRANDE"}], "COMERIO": [{"zone": "BO LAZOS", "area": "COMERIO"}, {"zone": "BO. R\u00cdO HONDO I", "area": "COMERIO"}], "VEGA ALTA": [{"zone": "BO. BAJURAS/VISTA DE LA VEGA", "area": "VEGA ALTA"}, {"zone": "BO. SABANA HOYOS", "area": "VEGA ALTA"}, {"zone": "Bo. Cerro Gordo", "area": "VEGA ALTA"}, {"zone": "Bo. Cienegueta", "area": "VEGA ALTA"}, {"zone": "GRAND PALM CERRO GORDO", "area": "VEGA ALTA"}, {"zone": "SABANA", "area": "VEGA ALTA"}, {"zone": "URB SANTA ANA", "area": "VEGA ALTA"}, {"zone": "URB VEGA DORADA", "area": "VEGA ALTA"}, {"area": "VEGA ALTA"}], "AIBONITO": [{"zone": "BO BO LLANOS", "area": "AIBONITO"}, {"zone": "BO LLANOS SECT SATURNINO", "area": "AIBONITO"}, {"zone": "PLATA", "area": "AIBONITO"}, {"zone": "URB SAN JOSE", "area": "AIBONITO"}], "RINCON": [{"zone": "BO CALVACHE", "area": "RINCON"}, {"zone": "BO CRUCES", "area": "RINCON"}, {"zone": "BO PUEBLO", "area": "RINCON"}, {"zone": "BO RIO GRANDE SECT LOS MANGOS", "area": "RINCON"}], "ANASCO": [{"zone": "Bo. Ovejas", "area": "ANASCO"}], "CIDRA": [{"zone": "BAYAMON", "area": "CIDRA"}, {"zone": "BO CEIBA", "area": "CIDRA"}, {"zone": "Bo. Rabanal", "area": "CIDRA"}, {"zone": "HACIENDA LA CIMA", "area": "CIDRA"}], "MOCA": [{"zone": "BO CAPA BZN 12427", "area": "MOCA"}, {"zone": "BO CENTRO SECTOR RODRIGUEZ", "area": "MOCA"}, {"zone": "BO CUCHILLAS LOPERENA 10292", "area": "MOCA"}, {"zone": "BO NARANJO", "area": "MOCA"}, {"zone": "BO VOLADORAS SECT PAJUIL", "area": "MOCA"}, {"zone": "BO. CUCHILLAS", "area": "MOCA"}, {"zone": "BO. PUEBLO", "area": "MOCA"}, {"zone": "Bo. Cerro Gordo", "area": "MOCA"}, {"zone": "RES PUB JOSE N GANDARA", "area": "MOCA"}, {"zone": "VOLADORA SEC SOTO", "area": "MOCA"}], "YABUCOA": [{"zone": "BO AGUACATE         RUTA 29027", "area": "YABUCOA"}, {"zone": "Bo. Jagueyes", "area": "YABUCOA"}, {"zone": "PARC PLAYITA RUTA 29060", "area": "YABUCOA"}], "JUANA DIAZ": [{"zone": "BO COLLORES/GUARAGUAO", "area": "JUANA DIAZ"}, {"zone": "BO. AMUELAS", "area": "JUANA DIAZ"}, {"zone": "BO. LA AGUILITA", "area": "JUANA DIAZ"}, {"zone": "COM. LLORENS TORRES", "area": "JUANA DIAZ"}, {"zone": "RES VILLA DEL PARQUE", "area": "JUANA DIAZ"}, {"zone": "Res. Hucares", "area": "JUANA DIAZ"}, {"zone": "URB CAMINO REAL", "area": "JUANA DIAZ"}, {"zone": "URB ESTANCIAS DEL SUR", "area": "JUANA DIAZ"}, {"zone": "URB GALICIAS DEL MAR", "area": "JUANA DIAZ"}, {"zone": "URB SANTA RITA II", "area": "JUANA DIAZ"}, {"zone": "URB. LAS FLORES", "area": "JUANA DIAZ"}, {"zone": "URB. REP. DEL CARMEN", "area": "JUANA DIAZ"}], "LARES": [{"zone": "Bo. Lares", "area": "LARES"}, {"zone": "EL JOBO / 7 CASAS DESP 2 PTE", "area": "LARES"}], "OROCOVIS": [{"zone": "  -  ", "area": "OROCOVIS"}], "ARECIBO": [{"zone": "AVE. EL COTO", "area": "ARECIBO"}, {"zone": "BO GARROCHALES", "area": "ARECIBO"}, {"zone": "BO HATO ABAJO", "area": "ARECIBO"}, {"zone": "BO JUNCOS", "area": "ARECIBO"}, {"zone": "BO. GARROCHALES", "area": "ARECIBO"}, {"zone": "BO. HATO ARRIBA", "area": "ARECIBO"}, {"zone": "BO. SABANA HOYOS", "area": "ARECIBO"}, {"zone": "BO. SANTANA", "area": "ARECIBO"}, {"zone": "Bo. Santana", "area": "ARECIBO"}, {"zone": "CANDELARIA RPTO SANTA MARIA", "area": "ARECIBO"}, {"zone": "CASCO URBANO ARECIBO", "area": "ARECIBO"}, {"zone": "FACTOR", "area": "ARECIBO"}, {"zone": "HOGAR SAN PABLO, URBAN", "area": "ARECIBO"}, {"zone": "ISLOTE", "area": "ARECIBO"}, {"zone": "OCEAN VIEW", "area": "ARECIBO"}, {"zone": "PARC PUEBLO NUEVOBAJADERO", "area": "ARECIBO"}, {"zone": "SABANA HOYOS", "area": "ARECIBO"}, {"zone": "SANTANA", "area": "ARECIBO"}, {"zone": "TANAMA", "area": "ARECIBO"}, {"zone": "URB MIRADOR VISTA AZUL", "area": "ARECIBO"}, {"zone": "URB. VILLA LOS SANTOS 1", "area": "ARECIBO"}, {"zone": "Urb. Duhamel", "area": "ARECIBO"}], "TOA ALTA": [{"zone": "Bo. Ortiz", "area": "TOA ALTA"}, {"zone": "QUEBRADA CRUZ", "area": "TOA ALTA"}, {"zone": "RIO LAJAS", "area": "TOA ALTA"}], "LAJAS": [{"zone": "Ave. 65 Infanteria", "area": "LAJAS"}, {"zone": "LA PARGUERAAL LADO PTO VIEJO", "area": "LAJAS"}, {"zone": "SECTOR MAGUAYO", "area": "LAJAS"}, {"zone": "URB EL VALLE", "area": "LAJAS"}, {"zone": "URB. ALTURAS DE LAJAS 2", "area": "LAJAS"}], "PE\u00d1UELAS": [], "ISABELLA": [], "SABANA GRANDE": [{"zone": "Casco Urbano Sab. Gran", "area": "SABANA GRANDE"}, {"zone": "Sector Machuchal", "area": "SABANA GRANDE"}], "SANTA ISABEL": [{"zone": "COM LA PLAYA", "area": "SANTA ISABEL"}, {"zone": "URB. PARQUE DE JACARAN", "area": "SANTA ISABEL"}], "SALINAS": [{"zone": "  -  ", "area": "SALINAS"}, {"zone": "MONTESORIA II", "area": "SALINAS"}, {"zone": "PAR VAZQUEZ SALINAS", "area": "SALINAS"}, {"zone": "SECTOR COCO NUEVO", "area": "SALINAS"}, {"zone": "Urb. La Margarita I amp II", "area": "SALINAS"}], "SAN SEBASTIAN": [{"zone": "BARRIO POZAS", "area": "SAN SEBASTIAN"}, {"zone": "BO POZAS SAN SEBASTIAN", "area": "SAN SEBASTIAN"}, {"zone": "BO POZASSCT LOS NOBLES", "area": "SAN SEBASTIAN"}, {"zone": "Comunidad Gonzalez", "area": "SAN SEBASTIAN"}], "HORMIGUEROS": [{"zone": "PAR SAN ROMUALDO", "area": "HORMIGUEROS"}, {"zone": "SECTOR HOYA GRANDE", "area": "HORMIGUEROS"}, {"zone": "Sector El 5", "area": "HORMIGUEROS"}], "AGUADILLA": [{"zone": "AGUADILLA", "area": "AGUADILLA"}, {"zone": "BO GUERRERO BZN 11341", "area": "AGUADILLA"}, {"zone": "BO MONTANA SEC CAMPO ALEGRE", "area": "AGUADILLA"}, {"zone": "BO. CORRALES", "area": "AGUADILLA"}, {"zone": "BO. PALMAR", "area": "AGUADILLA"}, {"zone": "BO. SAN ANTONIO", "area": "AGUADILLA"}, {"zone": "BO. VICTORIA", "area": "AGUADILLA"}, {"zone": "Bo. Corrales", "area": "AGUADILLA"}, {"zone": "CAMASEYES URB BRISAS PRADO ALT", "area": "AGUADILLA"}, {"zone": "CTAL ALTO ANTES DEL VERTEDERO", "area": "AGUADILLA"}, {"zone": "RAMEY PR 00604", "area": "AGUADILLA"}, {"zone": "RES CUESTA VIEJA", "area": "AGUADILLA"}, {"zone": "RES. LA MONTA\u00d1A", "area": "AGUADILLA"}, {"zone": "URB PUBLICA", "area": "AGUADILLA"}], "CULEBRA": [], "QUEBRADILLAS": [{"zone": "BO COCOS", "area": "QUEBRADILLAS"}, {"zone": "BO SAN JOSE/LOS IGLESIAS", "area": "QUEBRADILLAS"}, {"zone": "Bo. San Antonio", "area": "QUEBRADILLAS"}, {"zone": "Bo. Terranova", "area": "QUEBRADILLAS"}], "GUAYNABO": [{"zone": "BO FRAILES", "area": "GUAYNABO"}, {"zone": "BO MAMEY", "area": "GUAYNABO"}, {"zone": "BO RIO", "area": "GUAYNABO"}, {"zone": "MAMEY", "area": "GUAYNABO"}, {"zone": "SONADORA", "area": "GUAYNABO"}, {"zone": "URB EL JARDIN DE GUAYNABO", "area": "GUAYNABO"}, {"zone": "URB PRADO ALTO", "area": "GUAYNABO"}, {"zone": "URB. BUCARE", "area": "GUAYNABO"}, {"zone": "Urb. Villa Reales", "area": "GUAYNABO"}], "JUNCOS": [{"zone": "ESTANCIAS DE LA CEIBA", "area": "JUNCOS"}, {"zone": "URB HACIENDA DE TENAS", "area": "JUNCOS"}, {"zone": "URB SENDEROS DE JUNCOS", "area": "JUNCOS"}, {"zone": "VALENCIANO ARRIBA", "area": "JUNCOS"}, {"zone": "VIRGINIA VALLEY R055", "area": "JUNCOS"}], "CABO ROJO": [{"zone": "BO. LLANOS TUNA", "area": "CABO ROJO"}, {"zone": "ESTANCIAS NITO MARTY", "area": "CABO ROJO"}, {"zone": "HACIENDAS DE LA BAUME", "area": "CABO ROJO"}, {"zone": "SOLAR 7 EL COMBATE", "area": "CABO ROJO"}, {"zone": "Sector Combate", "area": "CABO ROJO"}], "CATANO": [{"zone": "Bo. Palmas", "area": "CATANO"}, {"zone": "RES JUANA MATOS IAVE BARBOSA", "area": "CATANO"}, {"zone": "URB PRADERA", "area": "CATANO"}], "CAROLINA": [{"zone": "Ave. 65 Infanteria", "area": "CAROLINA"}, {"zone": "BO CACAO", "area": "CAROLINA"}, {"zone": "BO CANOVANILLAS", "area": "CAROLINA"}, {"zone": "BO CEDROS X POLLERA AL FINAL", "area": "CAROLINA"}, {"zone": "Bo. Cacao", "area": "CAROLINA"}, {"zone": "Bo. Carruzos", "area": "CAROLINA"}, {"zone": "Bo. San Anton", "area": "CAROLINA"}, {"zone": "CANGREJO ARRIBA", "area": "CAROLINA"}, {"zone": "COND AMAPOLA", "area": "CAROLINA"}, {"zone": "COND LAGUNA GARDENS", "area": "CAROLINA"}, {"zone": "COND LAS GAVIOTAS", "area": "CAROLINA"}, {"zone": "COND MAR AZUL", "area": "CAROLINA"}, {"zone": "EXT LOS ANGELES", "area": "CAROLINA"}, {"zone": "HOYO MULAS", "area": "CAROLINA"}, {"zone": "JESUS MARIA SANROMA APARTMENTS", "area": "CAROLINA"}, {"zone": "RES LLORENS TORRES", "area": "CAROLINA"}, {"zone": "RES SABANA ABAJO", "area": "CAROLINA"}, {"zone": "SABANA ABAJO", "area": "CAROLINA"}, {"zone": "SAN ANTON", "area": "CAROLINA"}, {"zone": "SUPERIOR, CANOVANILLAS,", "area": "CAROLINA"}, {"zone": "TRUJILLO BAJO", "area": "CAROLINA"}, {"zone": "URB COUNTRY CLUB", "area": "CAROLINA"}, {"zone": "URB V ARRIBA HEIGHTS983", "area": "CAROLINA"}, {"zone": "URB VILLAS DEL PALMAR SUR", "area": "CAROLINA"}, {"zone": "URB. EXT. EL COMANDANT", "area": "CAROLINA"}, {"zone": "Urb. Los \u00c1ngeles", "area": "CAROLINA"}, {"zone": "Urb. Severo Quinones", "area": "CAROLINA"}, {"zone": "Urb. Villa Fontana Par", "area": "CAROLINA"}, {"zone": "Urb. Vistamar", "area": "CAROLINA"}], "BARRANQUITAS": [{"zone": "BARRANCAS", "area": "BARRANQUITAS"}, {"zone": "BO HELECHAL", "area": "BARRANQUITAS"}, {"zone": "BO HONDURAS EL PORTON", "area": "BARRANQUITAS"}, {"zone": "BO. LA TORRE", "area": "BARRANQUITAS"}], "ADJUNTAS": [{"zone": "BO JUAN GONZALEZ", "area": "ADJUNTAS"}, {"zone": "BO TANAMA", "area": "ADJUNTAS"}], "SAN GERMAN": [{"zone": "BARRIO MINILLAS", "area": "SAN GERMAN"}, {"zone": "BO. COTUI", "area": "SAN GERMAN"}, {"zone": "Bo. Duey Bajo", "area": "SAN GERMAN"}, {"zone": "PARCS SABANA ENEAS", "area": "SAN GERMAN"}, {"zone": "Sector Minillas Alto", "area": "SAN GERMAN"}, {"zone": "URB EL REAL", "area": "SAN GERMAN"}], "TOA BAJA": [{"zone": "Bo. Ingenio", "area": "TOA BAJA"}, {"zone": "CANDELARIA", "area": "TOA BAJA"}, {"zone": "SABANA SECA", "area": "TOA BAJA"}, {"zone": "URB LEVITTOWN", "area": "TOA BAJA"}, {"zone": "URB. 6TA LEVITTOWN", "area": "TOA BAJA"}, {"zone": "VILLA HOSTOS CAMPANILLA", "area": "TOA BAJA"}], "BAYAMON": [{"zone": "BO JUAN ASENCIO ANDALUZ LOPEZ", "area": "BAYAMON"}, {"zone": "BUENA VISTA", "area": "BAYAMON"}, {"zone": "COND REXVILLE PARK EDIF O", "area": "BAYAMON"}, {"zone": "SECTOR ARTEMIO ALGARIN DAJAOS", "area": "BAYAMON"}, {"zone": "URB CANA", "area": "BAYAMON"}, {"zone": "URB FOREST HILLS", "area": "BAYAMON"}, {"zone": "URB REPARTO FLAMINGO", "area": "BAYAMON"}, {"zone": "URB. IRLANDA HEIGHTS", "area": "BAYAMON"}, {"zone": "URB. RIVER VIEW", "area": "BAYAMON"}, {"zone": "Urb. Forest View", "area": "BAYAMON"}, {"zone": "Urb. Lomas Verdes", "area": "BAYAMON"}, {"zone": "Urb. Rexville", "area": "BAYAMON"}], "ARROYO": [{"zone": "Bo. Palmas", "area": "ARROYO"}], "CANOVANAS": [{"zone": "BO PALMA SOLA SECT EL HOYO", "area": "CANOVANAS"}, {"zone": "Bo. Campo Rico", "area": "CANOVANAS"}, {"zone": "Bo. Palma Sola", "area": "CANOVANAS"}, {"zone": "CANOVANAS", "area": "CANOVANAS"}, {"zone": "MANSIONES DEL TESORO", "area": "CANOVANAS"}, {"zone": "SECTOR PUENTE MORENO", "area": "CANOVANAS"}, {"zone": "Urb. River Garden", "area": "CANOVANAS"}], "AGUADA": [{"zone": "BO MAMEY", "area": "AGUADA"}, {"zone": "BO. ASOMANTE", "area": "AGUADA"}, {"zone": "BO. ATALAYA", "area": "AGUADA"}, {"zone": "BO. PIEDRAS BLANCAS", "area": "AGUADA"}, {"zone": "BO. TABLONAL", "area": "AGUADA"}, {"zone": "Bo. Cruces", "area": "AGUADA"}, {"zone": "Bo. Jaguey", "area": "AGUADA"}, {"zone": "CRUCES", "area": "AGUADA"}, {"zone": "Zona Urbana Aguada", "area": "AGUADA"}], "VILLALBA": [{"zone": "CASCO URBANO VILLALBA", "area": "VILLALBA"}, {"zone": "Sector Jovitos", "area": "VILLALBA"}, {"zone": "URB EST DEL MAYORAL/BO VACAS", "area": "VILLALBA"}], "GURABO": [{"zone": "  -  ", "area": "GURABO"}, {"zone": "BO MAMEY I", "area": "GURABO"}, {"zone": "BO. JAGUAL,LOS BEZARES", "area": "GURABO"}, {"zone": "COND VILLAS DEL ESTE", "area": "GURABO"}, {"zone": "SANTA BARBARA BO RINCON", "area": "GURABO"}, {"zone": "URB EL ENCANTO", "area": "GURABO"}, {"zone": "URB SANTA BARBARA", "area": "GURABO"}], "MARICAO": [{"zone": "BO BUCARABONES", "area": "MARICAO"}], "LAS PIEDRAS": [{"zone": "TEJAS-SECTOR LOS PERALES", "area": "LAS PIEDRAS"}, {"zone": "URB LA ESTANCIA", "area": "LAS PIEDRAS"}], "TRUJILLO ALTO": [{"zone": "BDA. GONZALEZ II", "area": "TRUJILLO ALTO"}, {"zone": "BO. CARRAIZO", "area": "TRUJILLO ALTO"}, {"zone": "BO. DOS BOCAS", "area": "TRUJILLO ALTO"}, {"zone": "BO. QUEBRADA NEGRITO", "area": "TRUJILLO ALTO"}, {"zone": "Bda. El Hoyo II", "area": "TRUJILLO ALTO"}, {"zone": "Bo. Carraizo", "area": "TRUJILLO ALTO"}, {"zone": "Bo. Las Cuevas", "area": "TRUJILLO ALTO"}, {"zone": "Bo. Quebrada Grande", "area": "TRUJILLO ALTO"}, {"zone": "Bo. Santo Domingo", "area": "TRUJILLO ALTO"}, {"zone": "CARRAIZO", "area": "TRUJILLO ALTO"}, {"zone": "CASCO URBANO TRUJ. ALT", "area": "TRUJILLO ALTO"}, {"zone": "COLINAS DE FAIR VIEW", "area": "TRUJILLO ALTO"}, {"zone": "LA GLORIA", "area": "TRUJILLO ALTO"}, {"zone": "PALMAS DE MONTEBELLO,LA CUEVAS", "area": "TRUJILLO ALTO"}, {"zone": "Parc. Ramon T. Colon", "area": "TRUJILLO ALTO"}, {"zone": "URB. COLINAS DE FAIR VIEW", "area": "TRUJILLO ALTO"}, {"zone": "URB. VALLE SAN JUAN, E", "area": "TRUJILLO ALTO"}, {"zone": "Urb. Lomas De Trujillo", "area": "TRUJILLO ALTO"}, {"zone": "Urb. Vista Del Rio", "area": "TRUJILLO ALTO"}], "CAMUY": [{"zone": "ABRA HONDA", "area": "CAMUY"}, {"zone": "BO ABRA HONDA", "area": "CAMUY"}, {"zone": "BO PUENTE PENA", "area": "CAMUY"}, {"zone": "BO YEGUADA-SECT ARIAS", "area": "CAMUY"}], "PONCE": [{"zone": "AVE LAS AMERICAS 32", "area": "PONCE"}, {"zone": "Ave. Las Am\u00e9ricas", "area": "PONCE"}, {"zone": "BDA CLAUSELLS", "area": "PONCE"}, {"zone": "BO LOS AUSUBOS", "area": "PONCE"}, {"zone": "BO REAL ANON - LAS MESAS", "area": "PONCE"}, {"zone": "BO. COTO LAUREL", "area": "PONCE"}, {"zone": "COM AMALIA MARIN PLAYA", "area": "PONCE"}, {"zone": "COND TWIN TOWERS URB SAN JORG", "area": "PONCE"}, {"zone": "Carr 2", "area": "PONCE"}, {"zone": "Casco Urbano Ponce", "area": "PONCE"}, {"zone": "ED PANCHITA APT 204", "area": "PONCE"}, {"zone": "GUARAGUAO SEC SANTA ROSA", "area": "PONCE"}, {"zone": "LAS AMERICAS HOUSING", "area": "PONCE"}, {"zone": "MACHUELO ABAJO", "area": "PONCE"}, {"zone": "PAR 110 BO MARUENO", "area": "PONCE"}, {"zone": "PARC EL TUQUE", "area": "PONCE"}, {"zone": "PERLA DEL BUCANA", "area": "PONCE"}, {"zone": "REPTO IND SAN RAFAEL", "area": "PONCE"}, {"zone": "RES. CARIBE", "area": "PONCE"}, {"zone": "SECTOR PUNTA DIAMANTE", "area": "PONCE"}, {"zone": "URB CONSTANCIA", "area": "PONCE"}, {"zone": "URB EL MONTE", "area": "PONCE"}, {"zone": "URB LOS CAOBOS", "area": "PONCE"}, {"zone": "URB MARIANI", "area": "PONCE"}, {"zone": "URB RIO CANAS", "area": "PONCE"}, {"zone": "URB SANTA AMERICA", "area": "PONCE"}, {"zone": "URB VILLA FLORES", "area": "PONCE"}, {"zone": "URB. ANAIDA", "area": "PONCE"}, {"zone": "URB. SANTIAGO IGLESIAS", "area": "PONCE"}, {"zone": "Urb. Las Delicias", "area": "PONCE"}, {"zone": "Urb. Los Caobos", "area": "PONCE"}], "JAYUYA": [{"zone": "  -  ", "area": "JAYUYA"}], "CAYEY": [{"zone": "BO FARALLON", "area": "CAYEY"}, {"zone": "BO LAS VEGAS-PONDEROSA-", "area": "CAYEY"}, {"zone": "BO QUEBRADA ARRIBA", "area": "CAYEY"}, {"zone": "BO TOITA QUENEPO", "area": "CAYEY"}, {"zone": "BO. RINC\u00d3N", "area": "CAYEY"}, {"zone": "Bo. Montellano", "area": "CAYEY"}, {"zone": "Bo. Rincon", "area": "CAYEY"}, {"zone": "Casco Urbano Cayey", "area": "CAYEY"}, {"zone": "RESD LUIS M MORALES", "area": "CAYEY"}], "MANATI": [{"zone": "BO MONTE BELLO", "area": "MANATI"}, {"zone": "Bo. Cantera", "area": "MANATI"}, {"zone": "Bo. Cordova Davila", "area": "MANATI"}, {"zone": "Bo. Coto Norte", "area": "MANATI"}, {"zone": "Bo. La Laguna", "area": "MANATI"}, {"zone": "Bo. Pugnado", "area": "MANATI"}, {"zone": "CARR 2, COTO N.", "area": "MANATI"}, {"zone": "LA LOMITADETRAS PITUSA", "area": "MANATI"}, {"zone": "MANATI", "area": "MANATI"}, {"zone": "MANATI PLAZA APARTMENTS", "area": "MANATI"}, {"zone": "PARCELAS MARQUEZ", "area": "MANATI"}, {"zone": "RIO ARRIBA SALIENTE", "area": "MANATI"}, {"zone": "URB FLAMBOYAN BASE 2", "area": "MANATI"}, {"zone": "URB PUB LOS MURALES", "area": "MANATI"}], "COAMO": [{"zone": "SAN ILDEFONSO", "area": "COAMO"}, {"zone": "URB MONTE FLORES/BO LAS FLORES", "area": "COAMO"}], "UTUADO": [{"zone": "  -  ", "area": "UTUADO"}, {"zone": "BO CAONILLAS", "area": "UTUADO"}, {"zone": "BO SALTO ABAJO INT", "area": "UTUADO"}, {"zone": "Bo. Caguanas", "area": "UTUADO"}, {"zone": "Bo. Vivi Abajo", "area": "UTUADO"}], "NAGUABO": [{"zone": "DAGUAO                   27039", "area": "NAGUABO"}, {"zone": "JARDINES DE LA VIA", "area": "NAGUABO"}, {"zone": "MARIANASECT JOSE LIMA 27006", "area": "NAGUABO"}, {"zone": "URB VISTA VERDE", "area": "NAGUABO"}], "SAN JUAN": [{"zone": "  -  ", "area": "SAN JUAN"}, {"zone": "** BEAUTY SALON **", "area": "SAN JUAN"}, {"zone": "ALAMEDA TOWERS 2", "area": "SAN JUAN"}, {"zone": "ALTURAS DE FAIR VIEW", "area": "SAN JUAN"}, {"zone": "APTS. COLINAS DE SAN JUAN", "area": "SAN JUAN"}, {"zone": "AVE. DE DIEGO", "area": "SAN JUAN"}, {"zone": "AVE. ROOSEVELT", "area": "SAN JUAN"}, {"zone": "BDA VENEZUELA", "area": "SAN JUAN"}, {"zone": "BO. CAIMITO ALTO", "area": "SAN JUAN"}, {"zone": "BO. CUPEY ALTO", "area": "SAN JUAN"}, {"zone": "BO. TORTUGO", "area": "SAN JUAN"}, {"zone": "BO. VILLA PALMERAS, SA", "area": "SAN JUAN"}, {"zone": "Bo. Caimito Bajo", "area": "SAN JUAN"}, {"zone": "CAIMITO", "area": "SAN JUAN"}, {"zone": "CALLE DEL PARQUE", "area": "SAN JUAN"}, {"zone": "COND ARANJUEZ", "area": "SAN JUAN"}, {"zone": "COND BAHIA PALACE", "area": "SAN JUAN"}, {"zone": "COND BORINQUEN TOWERS 1", "area": "SAN JUAN"}, {"zone": "COND CHALETS'S D' PARAISO", "area": "SAN JUAN"}, {"zone": "COND EL CENTRO", "area": "SAN JUAN"}, {"zone": "COND FLORIMAR GDN APTS", "area": "SAN JUAN"}, {"zone": "COND HATO REY PLAZA", "area": "SAN JUAN"}, {"zone": "COND KINGS COURT 81", "area": "SAN JUAN"}, {"zone": "COND LAGOON FLATS", "area": "SAN JUAN"}, {"zone": "COND MIRAMAR EMBASSY", "area": "SAN JUAN"}, {"zone": "COND PLAZA ANTILLANA*HAY ICC*", "area": "SAN JUAN"}, {"zone": "COND TORRE DE CERVANTES", "area": "SAN JUAN"}, {"zone": "CONDADO", "area": "SAN JUAN"}, {"zone": "CUPEY", "area": "SAN JUAN"}, {"zone": "EL CINCO", "area": "SAN JUAN"}, {"zone": "EXT LAS CASAS", "area": "SAN JUAN"}, {"zone": "GOBERNADOR PI\u00d1ERO", "area": "SAN JUAN"}, {"zone": "HATO REY CENTRAL", "area": "SAN JUAN"}, {"zone": "HATO REY NORTE", "area": "SAN JUAN"}, {"zone": "Isla Grande", "area": "SAN JUAN"}, {"zone": "JARDINES DE FRANCIA", "area": "SAN JUAN"}, {"zone": "JARDINES DE VALENCIA", "area": "SAN JUAN"}, {"zone": "MONACILLO", "area": "SAN JUAN"}, {"zone": "MONACILLO URBANO", "area": "SAN JUAN"}, {"zone": "PARADA 22", "area": "SAN JUAN"}, {"zone": "RES RAMOS ANTONINI", "area": "SAN JUAN"}, {"zone": "RES SAN ANTONIO", "area": "SAN JUAN"}, {"zone": "RES. NEMESIO CANALES", "area": "SAN JUAN"}, {"zone": "RES. RAMOS ANTONINI, R", "area": "SAN JUAN"}, {"zone": "Res. Monte Hatillo", "area": "SAN JUAN"}, {"zone": "Res. Quintana RP", "area": "SAN JUAN"}, {"zone": "Res. San Martin", "area": "SAN JUAN"}, {"zone": "SABANA LLANA NORTE", "area": "SAN JUAN"}, {"zone": "SABANA LLANA SUR", "area": "SAN JUAN"}, {"zone": "SAN JUAN PARK APTS", "area": "SAN JUAN"}, {"zone": "SANTURCE", "area": "SAN JUAN"}, {"zone": "UNIVERSIDAD", "area": "SAN JUAN"}, {"zone": "URB CAPARRA TERRACE", "area": "SAN JUAN"}, {"zone": "URB COUNTRY CLUB", "area": "SAN JUAN"}, {"zone": "URB EL COMANDANTE  15-12", "area": "SAN JUAN"}, {"zone": "URB EL DORADO", "area": "SAN JUAN"}, {"zone": "URB FAIR VIEW", "area": "SAN JUAN"}, {"zone": "URB HYDE PARK", "area": "SAN JUAN"}, {"zone": "URB LA RIVIERA", "area": "SAN JUAN"}, {"zone": "URB LAS LOMAS", "area": "SAN JUAN"}, {"zone": "URB LOS MAESTROS", "area": "SAN JUAN"}, {"zone": "URB PUB M A PEREZ", "area": "SAN JUAN"}, {"zone": "URB PUB SAN FERNANDO", "area": "SAN JUAN"}, {"zone": "URB PUERTO NUEVO", "area": "SAN JUAN"}, {"zone": "URB PUERTO NUEVO LOCAL C", "area": "SAN JUAN"}, {"zone": "URB RPTO METROPOLITANO", "area": "SAN JUAN"}, {"zone": "URB SAN AGUSTIN", "area": "SAN JUAN"}, {"zone": "URB SAN JOSE", "area": "SAN JUAN"}, {"zone": "URB SANTA ANA", "area": "SAN JUAN"}, {"zone": "URB SANTA BARBARA", "area": "SAN JUAN"}, {"zone": "URB VENUS GARDENS", "area": "SAN JUAN"}, {"zone": "URB VILLA ANDALUCIA", "area": "SAN JUAN"}, {"zone": "URB. JARD. SAN FRANCISCO", "area": "SAN JUAN"}, {"zone": "URB. LA RIVIERA", "area": "SAN JUAN"}, {"zone": "URB. LA VISTA", "area": "SAN JUAN"}, {"zone": "URB. MONTE HIEDRA", "area": "SAN JUAN"}, {"zone": "URB. PASEO REAL", "area": "SAN JUAN"}, {"zone": "URB. VENUS VARDENS SUR", "area": "SAN JUAN"}, {"zone": "URB. VILLAS DE CUPEY", "area": "SAN JUAN"}, {"zone": "Urb. Col. Monte Carlo", "area": "SAN JUAN"}, {"zone": "Urb. Colinas Verdes", "area": "SAN JUAN"}, {"zone": "Urb. El Cerezal", "area": "SAN JUAN"}, {"zone": "Urb. Fair View", "area": "SAN JUAN"}, {"zone": "Urb. Highland Park", "area": "SAN JUAN"}, {"zone": "Urb. Hillside", "area": "SAN JUAN"}, {"zone": "Urb. La Cumbre", "area": "SAN JUAN"}, {"zone": "Urb. Park Gardens", "area": "SAN JUAN"}, {"zone": "Urb. Portal De La Reina", "area": "SAN JUAN"}, {"zone": "Urb. Riveras De Cupey", "area": "SAN JUAN"}, {"zone": "Urb. San Agustin", "area": "SAN JUAN"}, {"zone": "Urb. San Francisco", "area": "SAN JUAN"}, {"zone": "Urb. Santiago Iglesias", "area": "SAN JUAN"}, {"zone": "Urb. Valencia", "area": "SAN JUAN"}, {"zone": "Urb. Venus Gard. Norte", "area": "SAN JUAN"}, {"zone": "VER 15/12URGENTE", "area": "SAN JUAN"}, {"zone": "VIEJO SAN JUAN", "area": "SAN JUAN"}, {"zone": "VILLA PALMERAS", "area": "SAN JUAN"}], "GUANICA": [], "CAGUAS": [{"zone": "  -  ", "area": "CAGUAS"}, {"zone": "BO CANABONCITO", "area": "CAGUAS"}, {"zone": "BO SAN ANTONIO", "area": "CAGUAS"}, {"zone": "CAGUAS", "area": "CAGUAS"}, {"zone": "CA\u00d1ABON", "area": "CAGUAS"}, {"zone": "PASEO EL VERDE WALK UPS", "area": "CAGUAS"}, {"zone": "TOMAS DE CASTRO", "area": "CAGUAS"}, {"zone": "URB MACHIN", "area": "CAGUAS"}, {"zone": "URB MARIOLGA", "area": "CAGUAS"}, {"zone": "URB VALLE TOLIMA", "area": "CAGUAS"}, {"zone": "URB VILLA BLANCA", "area": "CAGUAS"}, {"zone": "URB VILLA NUEVA", "area": "CAGUAS"}, {"zone": "Urb. Mirador De Bairoa", "area": "CAGUAS"}, {"zone": "VILLA DEL REY 4TA", "area": "CAGUAS"}], "CEIBA": [], "MOROVIS": [{"zone": "BO MONTELLANOS", "area": "MOROVIS"}, {"zone": "PAR SAN LORENZO 41", "area": "MOROVIS"}, {"zone": "UNIBON SECTOR PABON", "area": "MOROVIS"}], "NARANJITO": [{"zone": "Bo. Cedro Arriba", "area": "NARANJITO"}], "VEGA BAJA": [{"zone": "ALTURAS DE VEGA BAJA", "area": "VEGA BAJA"}, {"zone": "BO RIO ABAJO SEC HOYOS", "area": "VEGA BAJA"}, {"zone": "BO. PUGNADO DE AFUERA", "area": "VEGA BAJA"}, {"zone": "Bo. Algarrobo", "area": "VEGA BAJA"}, {"zone": "Bo. Almirante Norte", "area": "VEGA BAJA"}, {"zone": "Bo. Pugnado Adentro", "area": "VEGA BAJA"}, {"zone": "Bo. Pugnado De Afuera", "area": "VEGA BAJA"}, {"zone": "Bo. Rio Abajo", "area": "VEGA BAJA"}, {"zone": "Casco Urbano Vega Baja", "area": "VEGA BAJA"}, {"zone": "ED 27 CHALETS DE LA PLAYA", "area": "VEGA BAJA"}, {"zone": "PUG ADENTRO", "area": "VEGA BAJA"}, {"zone": "Parc. Amadeo", "area": "VEGA BAJA"}, {"zone": "Parc. Brisas De Tortuguero", "area": "VEGA BAJA"}, {"zone": "QUINTAS DE TORTUGUERO", "area": "VEGA BAJA"}, {"zone": "SECTOR GUARICO", "area": "VEGA BAJA"}, {"zone": "URB ALTURAS DE VEGA BAJA", "area": "VEGA BAJA"}, {"zone": "URB JARDINES DE VEGA BAJA", "area": "VEGA BAJA"}, {"zone": "URB QUINTAS DE TORTUGUERO", "area": "VEGA BAJA"}, {"zone": "Urb. Vega Baja Lakes", "area": "VEGA BAJA"}, {"zone": "Urb. Velomas", "area": "VEGA BAJA"}, {"zone": "VEGA BAJA LAKES", "area": "VEGA BAJA"}], "SAN LORENZO": [{"zone": "Sector Quebrada Honda", "area": "SAN LORENZO"}], "FAJARDO": [{"zone": "BO. FLORENCIO", "area": "FAJARDO"}, {"zone": "BO. JERUSALEN", "area": "FAJARDO"}, {"zone": "FAJARDO", "area": "FAJARDO"}, {"zone": "FLORENCIO", "area": "FAJARDO"}, {"zone": "MANSIONES DEL PICO DEL ESTE", "area": "FAJARDO"}, {"zone": "QUEBRADA FAJARDO", "area": "FAJARDO"}, {"zone": "QUEBRADA VUELTAS", "area": "FAJARDO"}], "MAYAGUEZ": [{"zone": "  -  ", "area": "MAYAGUEZ"}, {"zone": "BO LIMON ENTDA LA MARGARITA", "area": "MAYAGUEZ"}, {"zone": "BO QUEBRADA GRANDE", "area": "MAYAGUEZ"}, {"zone": "BO ROSARIO", "area": "MAYAGUEZ"}, {"zone": "BO SABALOS", "area": "MAYAGUEZ"}, {"zone": "BO. EL MAN\u00cd", "area": "MAYAGUEZ"}, {"zone": "Bo. Leguisano", "area": "MAYAGUEZ"}, {"zone": "Bo. Limon", "area": "MAYAGUEZ"}, {"zone": "CASCO URBANO MAYAG\u00dcEZ", "area": "MAYAGUEZ"}, {"zone": "COND SANTIAGO R PALMER", "area": "MAYAGUEZ"}, {"zone": "Casco Urbano Mayag\u00fcez", "area": "MAYAGUEZ"}, {"zone": "ENSANCHE MARTINEZ", "area": "MAYAGUEZ"}, {"zone": "MAYAGUEZ TERRACE", "area": "MAYAGUEZ"}, {"zone": "REPARTO MACIASBO LIMON", "area": "MAYAGUEZ"}, {"zone": "Res. Carmen", "area": "MAYAGUEZ"}, {"zone": "SANTA ROSA DE LIMA", "area": "MAYAGUEZ"}, {"zone": "URB ALEMANY", "area": "MAYAGUEZ"}, {"zone": "URB QUINTO CENTENARIO", "area": "MAYAGUEZ"}, {"zone": "URB SANTA MARIAJARDIN SANTAMA", "area": "MAYAGUEZ"}, {"zone": "URB. BUENAVENTURA", "area": "MAYAGUEZ"}, {"zone": "Urb. Altura De Mayag\u00fce", "area": "MAYAGUEZ"}, {"zone": "Urb. Ensanche Ramirez", "area": "MAYAGUEZ"}, {"zone": "Urb. Paseo Los Robles", "area": "MAYAGUEZ"}, {"zone": "Urb. Ponce De Leon", "area": "MAYAGUEZ"}, {"zone": "VILLA LAS VIOLETAS", "area": "MAYAGUEZ"}], "MAUNABO": [{"zone": "BO TALANTE", "area": "MAUNABO"}, {"zone": "SECTOR BORDALEZA BO EMAJAGUA", "area": "MAUNABO"}], "YAUCO": [{"zone": "Bo. Quebradas", "area": "YAUCO"}, {"zone": "LA JOYA", "area": "YAUCO"}, {"zone": "ZONA URBANA YAUCO", "area": "YAUCO"}]}