{"LUQUILLO": [], "COROZAL": [{"zone": "PALMAREJO", "area": "COROZAL"}], "CIALES": [{"zone": "CIALITOS", "area": "CIALES"}], "LAS MARIAS": [], "PATILLAS": [], "DORADO": [], "GUAYAMA": [], "HATILLO": [], "GUAYANILLA": [], "BARCELONETA": [], "AGUAS BUENAS": [], "HUMACAO": [], "VIEQUES": [], "FLORIDA": [], "LOIZA": [], "RIO GRANDE": [], "COMERIO": [], "VEGA ALTA": [], "AIBONITO": [], "RINCON": [], "ANASCO": [], "CIDRA": [], "MOCA": [], "YABUCOA": [], "JUANA DIAZ": [{"zone": "Bo. Jacaguas", "area": "JUANA DIAZ"}], "LARES": [], "OROCOVIS": [], "ARECIBO": [{"zone": "GARROCHALES", "area": "ARECIBO"}], "TOA ALTA": [], "LAJAS": [], "PE\u00d1UELAS": [], "ISABELLA": [], "SABANA GRANDE": [], "SANTA ISABEL": [], "SALINAS": [], "SAN SEBASTIAN": [], "HORMIGUEROS": [{"zone": "Sector El Hoyo", "area": "HORMIGUEROS"}], "AGUADILLA": [], "CULEBRA": [], "QUEBRADILLAS": [], "GUAYNABO": [], "JUNCOS": [], "CABO ROJO": [], "CATANO": [], "CAROLINA": [], "BARRANQUITAS": [], "ADJUNTAS": [], "SAN GERMAN": [], "TOA BAJA": [{"zone": "CANDELARIA", "area": "TOA BAJA"}], "BAYAMON": [{"zone": "PAJAROS", "area": "BAYAMON"}, {"zone": "URB BELLA VISTA GARDENS", "area": "BAYAMON"}], "ARROYO": [], "CANOVANAS": [], "AGUADA": [{"zone": "LAGUNAS", "area": "AGUADA"}], "VILLALBA": [], "GURABO": [], "MARICAO": [], "LAS PIEDRAS": [], "TRUJILLO ALTO": [], "CAMUY": [{"zone": "MEMBRILLO", "area": "CAMUY"}], "PONCE": [{"zone": "SEGUNDO", "area": "PONCE"}], "JAYUYA": [{"zone": "Bo. Jauca", "area": "JAYUYA"}], "CAYEY": [{"zone": "TOITA", "area": "CAYEY"}], "MANATI": [], "COAMO": [], "UTUADO": [], "NAGUABO": [], "SAN JUAN": [{"zone": "GOBERNADOR PI\u00d1ERO", "area": "SAN JUAN"}, {"zone": "SAN JUAN ANTIGUO", "area": "SAN JUAN"}], "GUANICA": [], "CAGUAS": [{"zone": "SAN ANTONIO", "area": "CAGUAS"}, {"zone": "URB VILLA BLANCA", "area": "CAGUAS"}], "CEIBA": [], "MOROVIS": [], "NARANJITO": [], "VEGA BAJA": [], "SAN LORENZO": [], "FAJARDO": [], "MAYAGUEZ": [], "MAUNABO": [], "YAUCO": []}