{"regions": [{"name": "Arecibo", "totalClients": 177369, "totalClientsWithoutService": 157, "totalClientsWithService": 177212, "totalClientsAffectedByPlannedOutage": 0, "totalClientsAffectedByLoadShed": 0, "percentageClientsWithoutService": 0.09, "percentageClientsWithService": 99.91}, {"name": "Bayamon", "totalClients": 216496, "totalClientsWithoutService": 1067, "totalClientsWithService": 215429, "totalClientsAffectedByPlannedOutage": 398, "totalClientsAffectedByLoadShed": 0, "percentageClientsWithoutService": 0.49, "percentageClientsWithService": 99.51}, {"name": "Carolina", "totalClients": 141663, "totalClientsWithoutService": 480, "totalClientsWithService": 141183, "totalClientsAffectedByPlannedOutage": 0, "totalClientsAffectedByLoadShed": 0, "percentageClientsWithoutService": 0.34, "percentageClientsWithService": 99.66}, {"name": "Caguas", "totalClients": 250514, "totalClientsWithoutService": 2875, "totalClientsWithService": 247639, "totalClientsAffectedByPlannedOutage": 2491, "totalClientsAffectedByLoadShed": 0, "percentageClientsWithoutService": 1.15, "percentageClientsWithService": 98.85}, {"name": "Mayaguez", "totalClients": 216605, "totalClientsWithoutService": 311, "totalClientsWithService": 216294, "totalClientsAffectedByPlannedOutage": 108, "totalClientsAffectedByLoadShed": 0, "percentageClientsWithoutService": 0.14, "percentageClientsWithService": 99.86}, {"name": "Ponce", "totalClients": 212508, "totalClientsWithoutService": 1450, "totalClientsWithService": 211058, "totalClientsAffectedByPlannedOutage": 1094, "totalClientsAffectedByLoadShed": 0, "percentageClientsWithoutService": 0.68, "percentageClientsWithService": 99.32}, {"name": "San Juan", "totalClients": 253068, "totalClientsWithoutService": 511, "totalClientsWithService": 252557, "totalClientsAffectedByPlannedOutage": 3, "totalClientsAffectedByLoadShed": 0, "percentageClientsWithoutService": 0.2, "percentageClientsWithService": 99.8}], "totals": {"totalClientsWithoutService": 6851, "totalClientsAffectedByLoadShed": 0, "totalClients": 1468223, "totalClientsWithService": 1461372, "totalPercentageWithoutService": 0.47, "totalClientsAffectedByPlannedOutage": 4094, "totalPercentageWithService": 99.53}, "timestamp": "01/13/2026 03:00 PM"}