{"LUQUILLO": [{"zone": "BO M DE PLATANO 3422001-18800", "area": "LUQUILLO"}, {"zone": "Planta AAA", "area": "LUQUILLO"}], "COROZAL": [{"zone": "Bo. Cibuco 2", "area": "COROZAL"}, {"zone": "PUEBLO", "area": "COROZAL"}], "CIALES": [{"zone": "BO FRONTON YUNES", "area": "CIALES"}], "LAS MARIAS": [], "PATILLAS": [{"zone": "BO APEADEROS SECTOR LOS MORALE", "area": "PATILLAS"}], "DORADO": [], "GUAYAMA": [], "HATILLO": [{"zone": "PUEBLO ANTES DEL SEC MOLINARY", "area": "HATILLO"}], "GUAYANILLA": [], "BARCELONETA": [], "AGUAS BUENAS": [], "HUMACAO": [], "VIEQUES": [], "FLORIDA": [], "LOIZA": [{"zone": "Bo. Mediania Alta", "area": "LOIZA"}, {"zone": "Sector Tocones", "area": "LOIZA"}, {"zone": "VILLAS DE MINI MINI", "area": "LOIZA"}], "RIO GRANDE": [{"zone": "PICO DEL ESTE/FLORIDA/EL YUNQU", "area": "RIO GRANDE"}], "COMERIO": [], "VEGA ALTA": [], "AIBONITO": [{"zone": "BO CUYON-EL FRESAL", "area": "AIBONITO"}, {"zone": "BO PASTO VILLA DE ALGARROBO", "area": "AIBONITO"}, {"zone": "Bo. Cuyon", "area": "AIBONITO"}, {"zone": "MERCEDITA SERRALLES - GS", "area": "AIBONITO"}], "RINCON": [], "ANASCO": [{"zone": "POSE DEL VALLE/PINALES", "area": "ANASCO"}], "CIDRA": [{"zone": "Bo. Ceiba", "area": "CIDRA"}], "MOCA": [], "YABUCOA": [{"zone": "BO. JUAN MARTIN", "area": "YABUCOA"}, {"zone": "PLAYA", "area": "YABUCOA"}, {"zone": "URB SANTA ELENA", "area": "YABUCOA"}], "JUANA DIAZ": [], "LARES": [], "OROCOVIS": [{"zone": "Bo. Bermejas", "area": "OROCOVIS"}, {"zone": "Bo. Gato", "area": "OROCOVIS"}], "ARECIBO": [{"zone": "BO BAJADERO", "area": "ARECIBO"}, {"zone": "BO ESPERANDA/CIENEGUETA/PALOMA", "area": "ARECIBO"}, {"zone": "BO HIGUILLAR RETO VALLE VERDE", "area": "ARECIBO"}, {"zone": "GARROCHALES", "area": "ARECIBO"}, {"zone": "JAREALITOS", "area": "ARECIBO"}, {"zone": "SEC MARCO SOTO LOS CANOS", "area": "ARECIBO"}, {"zone": "TANAMA", "area": "ARECIBO"}], "TOA ALTA": [], "LAJAS": [], "PE\u00d1UELAS": [{"zone": "JAGUAS", "area": "PE\u00d1UELAS"}], "ISABELLA": [], "SABANA GRANDE": [], "SANTA ISABEL": [{"zone": "BO PASO SECO/PARC VIEJAS", "area": "SANTA ISABEL"}], "SALINAS": [{"zone": "Bo. Palmas", "area": "SALINAS"}], "SAN SEBASTIAN": [], "HORMIGUEROS": [], "AGUADILLA": [{"zone": "Bo. Caimital Bajo", "area": "AGUADILLA"}], "CULEBRA": [], "QUEBRADILLAS": [{"zone": "CACAO", "area": "QUEBRADILLAS"}], "GUAYNABO": [{"zone": "Bo. Frailes", "area": "GUAYNABO"}, {"zone": "FRAILES", "area": "GUAYNABO"}, {"zone": "HATO NUEVO", "area": "GUAYNABO"}, {"zone": "PARC LOPEZ CASES", "area": "GUAYNABO"}], "JUNCOS": [{"zone": "LIRIOS", "area": "JUNCOS"}], "CABO ROJO": [{"zone": "BO EL COMBATE CASA DE PLAYA", "area": "CABO ROJO"}, {"zone": "BO JOYUDAS", "area": "CABO ROJO"}], "CATANO": [], "CAROLINA": [{"zone": "Bo. Barraza", "area": "CAROLINA"}, {"zone": "CEDRO", "area": "CAROLINA"}, {"zone": "URB LOS CACIQUES", "area": "CAROLINA"}, {"zone": "URB VILLA CAROLINA", "area": "CAROLINA"}], "BARRANQUITAS": [], "ADJUNTAS": [{"zone": "ENTRADA FRENTE HOGARES SEGUROS", "area": "ADJUNTAS"}], "SAN GERMAN": [{"zone": "Bo. Guama", "area": "SAN GERMAN"}], "TOA BAJA": [{"zone": "URB BRISAS DEL CAMPANERO", "area": "TOA BAJA"}], "BAYAMON": [{"zone": "Bo. Buena Vista", "area": "BAYAMON"}, {"zone": "Bo. Guaraguao Abajo", "area": "BAYAMON"}, {"zone": "Bo. Pajaros Americanos", "area": "BAYAMON"}, {"zone": "COND JARDINES DE CAPARRA", "area": "BAYAMON"}, {"zone": "MINILLAS", "area": "BAYAMON"}, {"zone": "URB SANTA ELENA", "area": "BAYAMON"}], "ARROYO": [], "CANOVANAS": [], "AGUADA": [], "VILLALBA": [{"zone": "BO JAGUEYES/TALLER PIPO", "area": "VILLALBA"}, {"zone": "URB SANTA ROSA", "area": "VILLALBA"}], "GURABO": [{"zone": "RINCON", "area": "GURABO"}, {"zone": "URB.LAS VEREDAS DE GURABO", "area": "GURABO"}], "MARICAO": [{"zone": "INDIERA ALTA", "area": "MARICAO"}], "LAS PIEDRAS": [{"zone": "BO.CEIBA NORTE           R-061", "area": "LAS PIEDRAS"}, {"zone": "BO.QUEBRADA ARENAS       R-062", "area": "LAS PIEDRAS"}, {"zone": "MONTONES 4 SEC POUPART", "area": "LAS PIEDRAS"}], "TRUJILLO ALTO": [{"zone": "BO CARRAIZO ALTO PUEBLITO", "area": "TRUJILLO ALTO"}, {"zone": "Bo. Quebrada Negrito", "area": "TRUJILLO ALTO"}, {"zone": "CARRAIZO", "area": "TRUJILLO ALTO"}, {"zone": "LAGO ESMERALDA", "area": "TRUJILLO ALTO"}], "CAMUY": [{"zone": "BO QUEBRADA", "area": "CAMUY"}, {"zone": "BO QUEBRADA SECT SANTIAGOVEGA", "area": "CAMUY"}, {"zone": "URB DEL CARMEN  BASE D", "area": "CAMUY"}], "PONCE": [{"zone": "BO SAN PATRICIO GUARAGUAO", "area": "PONCE"}, {"zone": "CANAS", "area": "PONCE"}, {"zone": "SEC BO LA MOCHA", "area": "PONCE"}, {"zone": "URB EL MONTE", "area": "PONCE"}], "JAYUYA": [{"zone": "BARRIO LA PICA", "area": "JAYUYA"}], "CAYEY": [{"zone": "BO JAJOME", "area": "CAYEY"}, {"zone": "BO MATON ARRIBA 1ER BAJO", "area": "CAYEY"}], "MANATI": [{"zone": "BO COTO NORTE", "area": "MANATI"}, {"zone": "MANATI", "area": "MANATI"}, {"zone": "PARC MARQUEZ-BO COTO NORTE", "area": "MANATI"}], "COAMO": [{"zone": "BO.PEDRO GARCIA/SECTOR UBILLAS", "area": "COAMO"}, {"zone": "COAMO PR", "area": "COAMO"}, {"zone": "RES EL EDEN/AL LADO HOSPITAL", "area": "COAMO"}, {"zone": "SEC SAN LUIS BO STA ANA", "area": "COAMO"}], "UTUADO": [{"zone": "BO MAMEYES SECT LIMON", "area": "UTUADO"}, {"zone": "BO RONCADOR", "area": "UTUADO"}], "NAGUABO": [{"zone": "BO CUBUY RL 27035", "area": "NAGUABO"}, {"zone": "BO MARIANA, R-27006", "area": "NAGUABO"}, {"zone": "DUQUE", "area": "NAGUABO"}], "SAN JUAN": [{"zone": "Ave. Roosevelt", "area": "SAN JUAN"}, {"zone": "Bo. Villa Palmeras Sa", "area": "SAN JUAN"}, {"zone": "QUEBRADA ARENAS", "area": "SAN JUAN"}, {"zone": "URB CIUDAD SENORIAL", "area": "SAN JUAN"}, {"zone": "URB EXT VILLA CAPARRA", "area": "SAN JUAN"}, {"zone": "URB LA CUMBRE", "area": "SAN JUAN"}, {"zone": "URB LA CUMBRE NO CK", "area": "SAN JUAN"}, {"zone": "URB LAS VIRTUDES", "area": "SAN JUAN"}, {"zone": "Urb. Monte Hiedra", "area": "SAN JUAN"}], "GUANICA": [], "CAGUAS": [{"zone": "BO BORINQUEN PARCELAS VIEJAS", "area": "CAGUAS"}, {"zone": "BO TURABO /LADO GARAGE GULF", "area": "CAGUAS"}, {"zone": "RIO CA\u00d1AS", "area": "CAGUAS"}, {"zone": "TOMAS DE CASTRO", "area": "CAGUAS"}, {"zone": "TOMAS DE CASTRO II", "area": "CAGUAS"}, {"zone": "URB EL RETIRO", "area": "CAGUAS"}], "CEIBA": [{"zone": "MACHOS", "area": "CEIBA"}], "MOROVIS": [], "NARANJITO": [], "VEGA BAJA": [], "SAN LORENZO": [{"zone": "BO ESPINO.SECT/MORENA", "area": "SAN LORENZO"}], "FAJARDO": [], "MAYAGUEZ": [{"zone": "GUANAJIBO", "area": "MAYAGUEZ"}, {"zone": "MODULO 5 PARQUE INDUSTRIA", "area": "MAYAGUEZ"}], "MAUNABO": [{"zone": "QUEBRADA ARENAS", "area": "MAUNABO"}], "YAUCO": [{"zone": "Bo. Algarrobo", "area": "YAUCO"}]}