{"regions": [{"name": "Arecibo", "totalClients": 177369, "totalClientsWithoutService": 1472, "totalClientsWithService": 175897, "totalClientsAffectedByPlannedOutage": 1402, "totalClientsAffectedByLoadShed": 0, "percentageClientsWithoutService": 0.83, "percentageClientsWithService": 99.17}, {"name": "Bayamon", "totalClients": 216496, "totalClientsWithoutService": 186, "totalClientsWithService": 216310, "totalClientsAffectedByPlannedOutage": 0, "totalClientsAffectedByLoadShed": 0, "percentageClientsWithoutService": 0.09, "percentageClientsWithService": 99.91}, {"name": "Carolina", "totalClients": 141663, "totalClientsWithoutService": 186, "totalClientsWithService": 141477, "totalClientsAffectedByPlannedOutage": 134, "totalClientsAffectedByLoadShed": 0, "percentageClientsWithoutService": 0.13, "percentageClientsWithService": 99.87}, {"name": "Caguas", "totalClients": 250514, "totalClientsWithoutService": 1286, "totalClientsWithService": 249228, "totalClientsAffectedByPlannedOutage": 484, "totalClientsAffectedByLoadShed": 0, "percentageClientsWithoutService": 0.51, "percentageClientsWithService": 99.49}, {"name": "Mayaguez", "totalClients": 216605, "totalClientsWithoutService": 21052, "totalClientsWithService": 195553, "totalClientsAffectedByPlannedOutage": 125, "totalClientsAffectedByLoadShed": 0, "percentageClientsWithoutService": 9.72, "percentageClientsWithService": 90.28}, {"name": "Ponce", "totalClients": 212508, "totalClientsWithoutService": 2324, "totalClientsWithService": 210184, "totalClientsAffectedByPlannedOutage": 1303, "totalClientsAffectedByLoadShed": 0, "percentageClientsWithoutService": 1.09, "percentageClientsWithService": 98.91}, {"name": "San Juan", "totalClients": 253068, "totalClientsWithoutService": 4384, "totalClientsWithService": 248684, "totalClientsAffectedByPlannedOutage": 343, "totalClientsAffectedByLoadShed": 0, "percentageClientsWithoutService": 1.73, "percentageClientsWithService": 98.27}], "totals": {"totalClientsWithoutService": 30890, "totalClientsAffectedByLoadShed": 0, "totalClients": 1468223, "totalClientsWithService": 1437333, "totalPercentageWithoutService": 2.1, "totalClientsAffectedByPlannedOutage": 3791, "totalPercentageWithService": 97.9}, "timestamp": "10/22/2025 12:00 PM"}