{"regions": [{"name": "Arecibo", "totalClients": 177369, "totalClientsWithoutService": 2746, "totalClientsWithService": 174623, "percentageClientsWithoutService": 1.55, "percentageClientsWithService": 98.45}, {"name": "Bayamon", "totalClients": 216496, "totalClientsWithoutService": 3399, "totalClientsWithService": 213097, "percentageClientsWithoutService": 1.57, "percentageClientsWithService": 98.43}, {"name": "Carolina", "totalClients": 141663, "totalClientsWithoutService": 8, "totalClientsWithService": 141655, "percentageClientsWithoutService": 0.01, "percentageClientsWithService": 99.99}, {"name": "Caguas", "totalClients": 250514, "totalClientsWithoutService": 211, "totalClientsWithService": 250303, "percentageClientsWithoutService": 0.08, "percentageClientsWithService": 99.92}, {"name": "Mayaguez", "totalClients": 216605, "totalClientsWithoutService": 1950, "totalClientsWithService": 214655, "percentageClientsWithoutService": 0.9, "percentageClientsWithService": 99.1}, {"name": "Ponce", "totalClients": 212508, "totalClientsWithoutService": 1183, "totalClientsWithService": 211325, "percentageClientsWithoutService": 0.56, "percentageClientsWithService": 99.44}, {"name": "San Juan", "totalClients": 253068, "totalClientsWithoutService": 743, "totalClientsWithService": 252325, "percentageClientsWithoutService": 0.29, "percentageClientsWithService": 99.71}], "totals": {"totalClientsWithoutService": 10240, "totalClients": 1468223, "totalClientsWithService": 1457983, "totalPercentageWithoutService": 0.7, "totalPercentageWithService": 99.3}, "timestamp": "11/30/2023 04:00 PM"}