{"regions": [{"name": "Arecibo", "totalClients": 177369, "totalClientsWithoutService": 68, "totalClientsWithService": 177301, "percentageClientsWithoutService": 0.04, "percentageClientsWithService": 99.96}, {"name": "Bayamon", "totalClients": 216496, "totalClientsWithoutService": 2072, "totalClientsWithService": 214424, "percentageClientsWithoutService": 0.96, "percentageClientsWithService": 99.04}, {"name": "Carolina", "totalClients": 141663, "totalClientsWithoutService": 3, "totalClientsWithService": 141660, "percentageClientsWithoutService": 0.0, "percentageClientsWithService": 100.0}, {"name": "Caguas", "totalClients": 250514, "totalClientsWithoutService": 508, "totalClientsWithService": 250006, "percentageClientsWithoutService": 0.2, "percentageClientsWithService": 99.8}, {"name": "Mayaguez", "totalClients": 216605, "totalClientsWithoutService": 1816, "totalClientsWithService": 214789, "percentageClientsWithoutService": 0.84, "percentageClientsWithService": 99.16}, {"name": "Ponce", "totalClients": 212508, "totalClientsWithoutService": 148, "totalClientsWithService": 212360, "percentageClientsWithoutService": 0.07, "percentageClientsWithService": 99.93}, {"name": "San Juan", "totalClients": 253068, "totalClientsWithoutService": 81, "totalClientsWithService": 252987, "percentageClientsWithoutService": 0.03, "percentageClientsWithService": 99.97}], "totals": {"totalClientsWithoutService": 4696, "totalClients": 1468223, "totalClientsWithService": 1463527, "totalPercentageWithoutService": 0.32, "totalPercentageWithService": 99.68}, "timestamp": "10/12/2023 04:00 PM"}