{"regions": [{"name": "Arecibo", "totalClients": 177369, "totalClientsWithoutService": 899, "totalClientsWithService": 176470, "percentageClientsWithoutService": 0.51, "percentageClientsWithService": 99.49}, {"name": "Bayamon", "totalClients": 216496, "totalClientsWithoutService": 31, "totalClientsWithService": 216465, "percentageClientsWithoutService": 0.01, "percentageClientsWithService": 99.99}, {"name": "Carolina", "totalClients": 141663, "totalClientsWithoutService": 2, "totalClientsWithService": 141661, "percentageClientsWithoutService": 0.0, "percentageClientsWithService": 100.0}, {"name": "Caguas", "totalClients": 250514, "totalClientsWithoutService": 165, "totalClientsWithService": 250349, "percentageClientsWithoutService": 0.07, "percentageClientsWithService": 99.93}, {"name": "Mayaguez", "totalClients": 216605, "totalClientsWithoutService": 300, "totalClientsWithService": 216305, "percentageClientsWithoutService": 0.14, "percentageClientsWithService": 99.86}, {"name": "Ponce", "totalClients": 212508, "totalClientsWithoutService": 28, "totalClientsWithService": 212480, "percentageClientsWithoutService": 0.01, "percentageClientsWithService": 99.99}, {"name": "San Juan", "totalClients": 253068, "totalClientsWithoutService": 55, "totalClientsWithService": 253013, "percentageClientsWithoutService": 0.02, "percentageClientsWithService": 99.98}], "totals": {"totalClientsWithoutService": 1480, "totalClients": 1468223, "totalClientsWithService": 1466743, "totalPercentageWithoutService": 0.1, "totalPercentageWithService": 99.9}, "timestamp": "11/11/2023 06:00 AM"}