{"regions": [{"name": "Arecibo", "totalClients": 177369, "totalClientsWithoutService": 234, "totalClientsWithService": 177135, "totalClientsAffectedByPlannedOutage": 0, "totalClientsAffectedByLoadShed": 0, "percentageClientsWithoutService": 0.13, "percentageClientsWithService": 99.87}, {"name": "Bayamon", "totalClients": 216496, "totalClientsWithoutService": 794, "totalClientsWithService": 215702, "totalClientsAffectedByPlannedOutage": 0, "totalClientsAffectedByLoadShed": 0, "percentageClientsWithoutService": 0.37, "percentageClientsWithService": 99.63}, {"name": "Carolina", "totalClients": 141663, "totalClientsWithoutService": 97, "totalClientsWithService": 141566, "totalClientsAffectedByPlannedOutage": 0, "totalClientsAffectedByLoadShed": 0, "percentageClientsWithoutService": 0.07, "percentageClientsWithService": 99.93}, {"name": "Caguas", "totalClients": 250514, "totalClientsWithoutService": 5779, "totalClientsWithService": 244735, "totalClientsAffectedByPlannedOutage": 0, "totalClientsAffectedByLoadShed": 0, "percentageClientsWithoutService": 2.31, "percentageClientsWithService": 97.69}, {"name": "Mayaguez", "totalClients": 216605, "totalClientsWithoutService": 8792, "totalClientsWithService": 207813, "totalClientsAffectedByPlannedOutage": 0, "totalClientsAffectedByLoadShed": 0, "percentageClientsWithoutService": 4.06, "percentageClientsWithService": 95.94}, {"name": "Ponce", "totalClients": 212508, "totalClientsWithoutService": 59, "totalClientsWithService": 212449, "totalClientsAffectedByPlannedOutage": 0, "totalClientsAffectedByLoadShed": 0, "percentageClientsWithoutService": 0.03, "percentageClientsWithService": 99.97}, {"name": "San Juan", "totalClients": 253068, "totalClientsWithoutService": 2570, "totalClientsWithService": 250498, "totalClientsAffectedByPlannedOutage": 0, "totalClientsAffectedByLoadShed": 0, "percentageClientsWithoutService": 1.02, "percentageClientsWithService": 98.98}], "totals": {"totalClientsWithoutService": 18325, "totalClientsAffectedByLoadShed": 0, "totalClients": 1468223, "totalClientsWithService": 1449898, "totalPercentageWithoutService": 1.25, "totalClientsAffectedByPlannedOutage": 0, "totalPercentageWithService": 98.75}, "timestamp": "02/15/2026 01:00 AM"}