{"regions": [{"name": "Arecibo", "totalClients": 177369, "totalClientsWithoutService": 955, "percentageClientsWithoutService": 0.54}, {"name": "Bayamon", "totalClients": 216496, "totalClientsWithoutService": 135, "percentageClientsWithoutService": 0.06}, {"name": "Carolina", "totalClients": 141663, "totalClientsWithoutService": 682, "percentageClientsWithoutService": 0.48}, {"name": "Caguas", "totalClients": 250514, "totalClientsWithoutService": 1193, "percentageClientsWithoutService": 0.48}, {"name": "Mayaguez", "totalClients": 216605, "totalClientsWithoutService": 20074, "percentageClientsWithoutService": 9.27}, {"name": "Ponce", "totalClients": 212508, "totalClientsWithoutService": 10867, "percentageClientsWithoutService": 5.11}, {"name": "San Juan", "totalClients": 253068, "totalClientsWithoutService": 69, "percentageClientsWithoutService": 0.03}], "totals": {"totalClientsWithoutService": 33975, "totalClients": 1468223, "totalPercentage": 2.31}}