{"regions": [{"name": "Arecibo", "totalClients": 177369, "totalClientsWithoutService": 34, "totalClientsWithService": 177335, "totalClientsAffectedByPlannedOutage": 0, "totalClientsAffectedByLoadShed": 0, "percentageClientsWithoutService": 0.02, "percentageClientsWithService": 99.98}, {"name": "Bayamon", "totalClients": 216496, "totalClientsWithoutService": 313, "totalClientsWithService": 216183, "totalClientsAffectedByPlannedOutage": 0, "totalClientsAffectedByLoadShed": 0, "percentageClientsWithoutService": 0.14, "percentageClientsWithService": 99.86}, {"name": "Carolina", "totalClients": 141663, "totalClientsWithoutService": 2, "totalClientsWithService": 141661, "totalClientsAffectedByPlannedOutage": 0, "totalClientsAffectedByLoadShed": 0, "percentageClientsWithoutService": 0.0, "percentageClientsWithService": 100.0}, {"name": "Caguas", "totalClients": 250514, "totalClientsWithoutService": 899, "totalClientsWithService": 249615, "totalClientsAffectedByPlannedOutage": 32, "totalClientsAffectedByLoadShed": 0, "percentageClientsWithoutService": 0.36, "percentageClientsWithService": 99.64}, {"name": "Mayaguez", "totalClients": 216605, "totalClientsWithoutService": 198, "totalClientsWithService": 216407, "totalClientsAffectedByPlannedOutage": 0, "totalClientsAffectedByLoadShed": 0, "percentageClientsWithoutService": 0.09, "percentageClientsWithService": 99.91}, {"name": "Ponce", "totalClients": 212508, "totalClientsWithoutService": 6273, "totalClientsWithService": 206235, "totalClientsAffectedByPlannedOutage": 5009, "totalClientsAffectedByLoadShed": 0, "percentageClientsWithoutService": 2.95, "percentageClientsWithService": 97.05}, {"name": "San Juan", "totalClients": 253068, "totalClientsWithoutService": 55, "totalClientsWithService": 253013, "totalClientsAffectedByPlannedOutage": 0, "totalClientsAffectedByLoadShed": 0, "percentageClientsWithoutService": 0.02, "percentageClientsWithService": 99.98}], "totals": {"totalClientsWithoutService": 7774, "totalClientsAffectedByLoadShed": 0, "totalClients": 1468223, "totalClientsWithService": 1460449, "totalPercentageWithoutService": 0.53, "totalClientsAffectedByPlannedOutage": 5041, "totalPercentageWithService": 99.47}, "timestamp": "01/27/2026 11:00 AM"}