{"regions": [{"name": "Arecibo", "totalClients": 177369, "totalClientsWithoutService": 123, "totalClientsWithService": 177246, "percentageClientsWithoutService": 0.07, "percentageClientsWithService": 99.93}, {"name": "Bayamon", "totalClients": 216496, "totalClientsWithoutService": 294, "totalClientsWithService": 216202, "percentageClientsWithoutService": 0.14, "percentageClientsWithService": 99.86}, {"name": "Carolina", "totalClients": 141663, "totalClientsWithoutService": 577, "totalClientsWithService": 141086, "percentageClientsWithoutService": 0.41, "percentageClientsWithService": 99.59}, {"name": "Caguas", "totalClients": 250514, "totalClientsWithoutService": 353, "totalClientsWithService": 250161, "percentageClientsWithoutService": 0.14, "percentageClientsWithService": 99.86}, {"name": "Mayaguez", "totalClients": 216605, "totalClientsWithoutService": 43, "totalClientsWithService": 216562, "percentageClientsWithoutService": 0.02, "percentageClientsWithService": 99.98}, {"name": "Ponce", "totalClients": 212508, "totalClientsWithoutService": 55, "totalClientsWithService": 212453, "percentageClientsWithoutService": 0.03, "percentageClientsWithService": 99.97}, {"name": "San Juan", "totalClients": 253068, "totalClientsWithoutService": 255, "totalClientsWithService": 252813, "percentageClientsWithoutService": 0.1, "percentageClientsWithService": 99.9}], "totals": {"totalClientsWithoutService": 1700, "totalClients": 1468223, "totalClientsWithService": 1466523, "totalPercentageWithoutService": 0.12, "totalPercentageWithService": 99.88}, "timestamp": "06/22/2023 06:00 AM"}