{"regions": [{"name": "Arecibo", "totalClients": 177369, "totalClientsWithoutService": 23969, "totalClientsWithService": 153400, "totalClientsAffectedByPlannedOutage": 0, "percentageClientsWithoutService": 13.51, "percentageClientsWithService": 86.49}, {"name": "Mayaguez", "totalClients": 216605, "totalClientsWithoutService": 10666, "totalClientsWithService": 205939, "totalClientsAffectedByPlannedOutage": 0, "percentageClientsWithoutService": 4.92, "percentageClientsWithService": 95.08}, {"name": "Bayamon", "totalClients": 216496, "totalClientsWithoutService": 14509, "totalClientsWithService": 201987, "totalClientsAffectedByPlannedOutage": 0, "percentageClientsWithoutService": 6.7, "percentageClientsWithService": 93.3}, {"name": "San Juan", "totalClients": 253068, "totalClientsWithoutService": 30978, "totalClientsWithService": 222090, "totalClientsAffectedByPlannedOutage": 0, "percentageClientsWithoutService": 12.24, "percentageClientsWithService": 87.76}, {"name": "Carolina", "totalClients": 141663, "totalClientsWithoutService": 15230, "totalClientsWithService": 126433, "totalClientsAffectedByPlannedOutage": 0, "percentageClientsWithoutService": 10.75, "percentageClientsWithService": 89.25}, {"name": "Caguas", "totalClients": 250514, "totalClientsWithoutService": 25858, "totalClientsWithService": 224656, "totalClientsAffectedByPlannedOutage": 0, "percentageClientsWithoutService": 10.32, "percentageClientsWithService": 89.68}, {"name": "Ponce", "totalClients": 212508, "totalClientsWithoutService": 1666, "totalClientsWithService": 210842, "totalClientsAffectedByPlannedOutage": 0, "percentageClientsWithoutService": 0.78, "percentageClientsWithService": 99.22}], "totals": {"totalClientsWithoutService": 122876, "totalClients": 1468223, "totalClientsWithService": 1345347, "totalPercentageWithoutService": 8.37, "totalClientsAffectedByPlannedOutage": 0, "totalPercentageWithService": 91.63}, "timestamp": "08/19/2024 08:00 PM"}