{"regions": [{"name": "Arecibo", "totalClients": 177369, "totalClientsWithoutService": 113, "totalClientsWithService": 177256, "totalClientsAffectedByPlannedOutage": 0, "percentageClientsWithoutService": 0.06, "percentageClientsWithService": 99.94}, {"name": "Bayamon", "totalClients": 216496, "totalClientsWithoutService": 413, "totalClientsWithService": 216083, "totalClientsAffectedByPlannedOutage": 0, "percentageClientsWithoutService": 0.19, "percentageClientsWithService": 99.81}, {"name": "Mayaguez", "totalClients": 216605, "totalClientsWithoutService": 2816, "totalClientsWithService": 213789, "totalClientsAffectedByPlannedOutage": 0, "percentageClientsWithoutService": 1.3, "percentageClientsWithService": 98.7}, {"name": "San Juan", "totalClients": 253068, "totalClientsWithoutService": 539, "totalClientsWithService": 252529, "totalClientsAffectedByPlannedOutage": 0, "percentageClientsWithoutService": 0.21, "percentageClientsWithService": 99.79}, {"name": "Carolina", "totalClients": 141663, "totalClientsWithoutService": 43, "totalClientsWithService": 141620, "totalClientsAffectedByPlannedOutage": 0, "percentageClientsWithoutService": 0.03, "percentageClientsWithService": 99.97}, {"name": "Caguas", "totalClients": 250514, "totalClientsWithoutService": 2711, "totalClientsWithService": 247803, "totalClientsAffectedByPlannedOutage": 0, "percentageClientsWithoutService": 1.08, "percentageClientsWithService": 98.92}, {"name": "Ponce", "totalClients": 212508, "totalClientsWithoutService": 10117, "totalClientsWithService": 202391, "totalClientsAffectedByPlannedOutage": 0, "percentageClientsWithoutService": 4.76, "percentageClientsWithService": 95.24}], "totals": {"totalClientsWithoutService": 16752, "totalClients": 1468223, "totalClientsWithService": 1451471, "totalPercentageWithoutService": 1.14, "totalClientsAffectedByPlannedOutage": 0, "totalPercentageWithService": 98.86}, "timestamp": "02/08/2024 04:00 AM"}